Workbook
Name MATRIX_PLAN: DANE!$Q$4:$Q$6
Name ON: DANE!$P$10

Sheet USER GUIDE
A1: SUPPORT
A2: W przypadku kłopotów lub pytań - napisz do maciej.andrzejewski@amrest.eu załączając plik, którego używasz wraz z opisem tego co się stało.
A4: W całym pliku uzupełniaj tylko żółte pola. Większość pól ma opis w komentarzu, który wyjaśnia skąd bierze się jakaś wartość lub jak jest obliczana. Wszystkie księgowania i obliczenia są potwierdzone z Payroll.
A5: Po tym jak zaplanujesz dany miesiąc kliknij Plik > Zapisz jako > MPK_Nazwamiesiąca
A6: Wklejanie AOP oraz Planu TPLH
A7: W Amreport wygeneruj dane AOP, koniecznie z rozwiniętymi wszystkimi kategoriami COL, a następnie wyeksportuj go do excela.
A8: Otwórz pobrany plik a następnie kliknij w lewym górnym rogu aby zaznaczyć cały arkusz i naciśnij CTRL+C
A9: Otwórz zakładkę AOP w kalkulatorze kosztów pracy. Kliknij w komórkę A1 w lewym górnym rogu a następnie wklej AOP skrótem klawiaturowym CTRL+V
A11: Przejdź do arkusza TPLH PLAN i wklej otrzymany od DM plan TPLH na cały rok. Wklejając użyj funkcji "wklej wartości".
A13: Planowanie nowego miesiąca - TARGET
A14: W żółtym polu z listy rozwijanej wybierz swój numer MPK
A16: Z listy rozwijanej wybierz miesiąc, który chcesz zaplanować. Wprowadź ilość dni otwartej kawiarni w miesiącu.
... A83: Wersja do druku jest wyskalowana do poniższego widoku. Pozostałe strony nie będą się drukować.

Sheet Rezerwa urlopowa
B1: Krok 1
B3: Korzystając z raportu P&L, przejdź do G&L Listingu w na koncie Payroll Manager
B18: Krok 2
B20: Przepisz kwotę rezerwy z poprzedniego miesiąca w poniższą tabelkę
B29: Krok 3
B31: Przejdź do AmReports -> Online Reports -> Monthly Reports -> Urlopy
B55: Do tabelki poniżej przepisz wartosci z kolumny "Urlop Rezerwa (na dd.mm.rrrr)" dla SM i podwładnych.
A78: NARZĘDZIE
B80: UZUPEŁNIJ tylko żółte pola
B82: MPK restauracji | C82: =CALCULATOR!F1 -> 108120
B83: Nazwa restauracji | C83: =CALCULATOR!C1 -> SBX Warszawa Janki
B84: rezerwa na miesiąc | C84: =CALCULATOR!C5 -> WRZESIEŃ
A86: lp. | B86: Nazwisko i Imię pracownika | C86: ilość dni urlopu niewykorzystanego /dni/ | D86: stawka miesięczna wynagrodzenia brutto /zł/ | E86: kwota rezerwy konto księgowe 40510610 | F86: składka ZUS konto księgowe 40610110 | G86: RAZEM rezerwa na niewykorzystany urlop (Razem rezerwa + ZUS)
A87: 1 | B87: =IF(CALCULATOR!I3="","",CALCULATOR!I3) -> Dawid Szeluga | C87: 2 | D87: =CALCULATOR!L3*CALCULATOR!K3 -> 7200 | E87: =ROUND((D87/21)*C87,0) -> 686 | F87: =ROUND(E87*0.195,0) -> 134 | G87: =E87+F87 -> 820
A88: 2 | B88: =IF(CALCULATOR!I4="","",CALCULATOR!I4) -> Dawid Apel | C88: 4 | D88: =CALCULATOR!L4*CALCULATOR!K4 -> 6300 | E88: =ROUND((D88/21)*C88,0) -> 1200 | F88: =ROUND(E88*0.195,0) -> 234 | G88: =E88+F88 -> 1434
A89: 3 | B89: =IF(CALCULATOR!I5="","",CALCULATOR!I5) -> Zuzanna Makowska | C89: 1 | D89: =CALCULATOR!L5*CALCULATOR!K5 -> 2632.5 | E89: =ROUND((D89/21)*C89,0) -> 125 | F89: =ROUND(E89*0.195,0) -> 24 | G89: =E89+F89 -> 149
A90: 4 | B90: =IF(CALCULATOR!I6="","",CALCULATOR!I6) -> Weronika Bieńkowska | C90: 4 | D90: =CALCULATOR!L6*CALCULATOR!K6 -> 2800 | E90: =ROUND((D90/21)*C90,0) -> 533 | F90: =ROUND(E90*0.195,0) -> 104 | G90: =E90+F90 -> 637
A91: 5 | B91: =IF(CALCULATOR!I7="","",CALCULATOR!I7) -> Nikola Studzińska | C91: 4 | D91: =CALCULATOR!L7*CALCULATOR!K7 -> 1150 | E91: =ROUND((D91/21)*C91,0) -> 219 | F91: =ROUND(E91*0.195,0) -> 43 | G91: =E91+F91 -> 262
A92: 6 | B92: =IF(CALCULATOR!I8="","",CALCULATOR!I8) -> Kamil Kamiński | D92: =CALCULATOR!L8*CALCULATOR!K8 -> 5600 | E92: =ROUND((D92/21)*C92,0) -> 0 | F92: =ROUND(E92*0.195,0) -> 0 | G92: =E92+F92 -> 0
A93: 7 | B93: =IF(CALCULATOR!I9="","",CALCULATOR!I9) | D93: =CALCULATOR!L9*CALCULATOR!K9 -> 0 | E93: =ROUND((D93/21)*C93,0) -> 0 | F93: =ROUND(E93*0.195,0) -> 0 | G93: =E93+F93 -> 0
A94: 8 | B94: =IF(CALCULATOR!I10="","",CALCULATOR!I10) | D94: =CALCULATOR!L10*CALCULATOR!K10 -> 0 | E94: =ROUND((D94/21)*C94,0) -> 0 | F94: =ROUND(E94*0.195,0) -> 0 | G94: =E94+F94 -> 0
A95: 9 | B95: =IF(CALCULATOR!I11="","",CALCULATOR!I11) | D95: =CALCULATOR!L11*CALCULATOR!K11 -> 0 | E95: =ROUND((D95/21)*C95,0) -> 0 | F95: =ROUND(E95*0.195,0) -> 0 | G95: =E95+F95 -> 0
A96: 10 | B96: =IF(CALCULATOR!I12="","",CALCULATOR!I12) | D96: =CALCULATOR!L12*CALCULATOR!K12 -> 0 | E96: =ROUND((D96/21)*C96,0) -> 0 | F96: =ROUND(E96*0.195,0) -> 0 | G96: =E96+F96 -> 0
A97: 11 | B97: Manager Bench | D97: =CALCULATOR!L13*CALCULATOR!K13 -> 0 | E97: =ROUND((D97/21)*C97,0) -> 0 | F97: =ROUND(E97*0.195,0) -> 0 | G97: =E97+F97 -> 0
A98: 12 | B98: Manager Maternity | E98: =ROUND((D98/21)*C98,0) -> 0 | F98: =ROUND(E98*0.195,0) -> 0 | G98: =E98+F98 -> 0
A99: 13 | B99: Manager Maternity | E99: =ROUND((D99/21)*C99,0) -> 0 | F99: =ROUND(E99*0.195,0) -> 0 | G99: =E99+F99 -> 0
A100: 14 | E100: =ROUND((D100/21)*C100,0) -> 0 | F100: =ROUND(E100*0.195,0) -> 0 | G100: =E100+F100 -> 0
A101: 15 | E101: =ROUND((D101/21)*C101,0) -> 0 | F101: =ROUND(E101*0.195,0) -> 0 | G101: =E101+F101 -> 0
B102: RAZEM | C102: =SUM(C87:C101) -> 15 | D102: =SUM(D87:D101) -> 25682.5 | E102: =SUM(E87:E101) -> 2763 | F102: =SUM(F87:F101) -> 539 | G102: =SUM(G87:G101) -> 3302
C104: wprowadź wartość rezerwy z zeszłego (starego) miesiąca | D104: -127 | F104: =ROUND(D104*0.195,0) -> -25 | G104: =D104+F104 -> -152
F105: Rezerwa z nowego miesiąca | G105: =G102 -> 3302
F106: Kwota do raportu DOS+ | G106: =G105-G104 -> 3454

Sheet CALCULATOR
B1: KAWIARNIA | C1: =IFERROR(VLOOKUP(F1,DANE!$AA$3:$AB$100,2,FALSE),"") -> SBX Warszawa Janki | F1: 108120 | H1: MANAGER TARGET | I1: Imię i Nazwisko | J1: Stanowisko | K1: Wymiar etatu | L1: Stawka brutto | M1: Planowany czas pracy | N1: Zwolnienie lekarskie | O1: Urlop | P1: Bonus Plan | Q1: ON | R1: MANAGER ESTIMATION | S1: Rzeczywisty czas pracy | T1: Zwolnienie lekarskie | U1: Urlop | V1: Bonus Estimation | W1: Store cost | X1: Etat | Y1: VARIABLES | AA1: MANAGER - TARGET | AB1: Basic salary manager | AC1: Bonus Plan | AD1: Social insurance | AE1: FGŚP + Fundusz Pracy | AF1: Equivalent | AG1: PFRON | AH1: Comp&Ben | AI1: JPA Accrual | AJ1: COL TOTAL | AL1: MANAGER - SICK LEAVE | AM1: Basic salary manager | AN1: Social insurance: | AO1: COL TOTAL | AP1: Sick Leave Salary | AX1: MANAGER - ESTIMATION | AY1: Basic salary manager | AZ1: Bonus Plan | BA1: Social insurance | BB1: FGŚP + Fundusz Pracy | BC1: Equivalent | BD1: PFRON | BE1: Comp&Ben | BF1: JPA Accrual | BG1: COL TOTAL | BI1: MANAGER - SICK LEAVE | BJ1: Basic salary manager | BK1: Social insurance: | BL1: COL TOTAL | BM1: Sick Leave Salary
I3: Dawid Szeluga | J3: SM | K3: 1 | L3: 7200 | M3: 176 | S3: 176 | W3: 1 | X3: =IFERROR(IF(Q3="Tak",K3*$C$8/8*7*W3,K3*$C$8),"") -> 176 | Y3: SOCIAL INSURANCE | AB3: =K3*L3*W3-AM3 -> 7200 | AC3: =P3 -> 0 | AD3: =(AB3+AC3+AH3+AI3)*$Y$4-AN3 -> 1331.8831 | AE3: =(AB3+AC3+AH3+AI3)*$Y$6 -> 200.6085 | AF3: =(IFERROR(VLOOKUP(J3,DANE!$B$3:$H$7,5,FALSE),"0")*K3)*W3 -> 300 | AG3: =K3*$Y$13*W3 -> 200 | AH3: =IFERROR(VLOOKUP(J3,DANE!$B$2:$I$7,7,FALSE),"0")*W3 -> 300 | AI3: =IF(J3="SM","367","0")*K3*W3 -> 367 | AJ3: =SUM(AB3:AI3) -> 9899.4916 | AM3: =L3/$Y$18*N3*$AP$3 -> 0 | AN3: =AM3*$Y$4*$AP$3 -> 0 | AO3: =SUM(AM3:AN3) -> 0 | AP3: 0.2 | AY3: =K3*L3*W3-BJ3 -> 7200 | AZ3: =V3 -> 0 | BA3: =(AY3+AZ3+BE3+BF3)*$Y$4-BK3 -> 1331.8831 | BB3: =(AY3+AZ3+BE3+BF3)*$Y$6 -> 200.6085 | BC3: =IFERROR(VLOOKUP(J3,DANE!$B$3:$H$7,5,FALSE),"0")*K3*W3 -> 300 | BD3: =K3*$Y$13*W3 -> 200 | BE3: =IFERROR(VLOOKUP(J3,DANE!$B$2:$I$7,7,FALSE),"0")*W3 -> 300 | BF3: =IF(J3="SM","367","0")*K3*W3 -> 367 | BG3: =SUM(AY3:BF3) -> 9899.4916 | BJ3: =L3/$Y$18*T3*$BM$3 -> 0 | BK3: =BJ3*$Y$4*$BM$3 -> 0 | BL3: =SUM(BJ3:BK3) -> 0 | BM3: 0.2
B4: COL | C4: TARGET | D4: AOP | E4: ESTIMATION | F4: P&L | I4: Dawid Apel | J4: ASM | K4: 1 | L4: 6300 | M4: 176 | S4: 176 | W4: 1 | X4: =IFERROR(IF(Q4="Tak",K4*$C$8/8*7*W4,K4*$C$8),"") -> 176 | Y4: =DANE!E3 -> 0.1693 | AB4: =K4*L4*W4-AM4 -> 6300 | AC4: =P4 -> 0 | AD4: =(AB4+AC4+AH4+AI4)*$Y$4-AN4 -> 1108.915 | AE4: =(AB4+AC4+AH4+AI4)*$Y$6 -> 167.025 | AF4: =(IFERROR(VLOOKUP(J4,DANE!$B$3:$H$7,5,FALSE),"0")*K4)*W4 -> 300 | AG4: =K4*$Y$13*W4 -> 200 | AH4: =IFERROR(VLOOKUP(J4,DANE!$B$2:$I$7,7,FALSE),"0")*W4 -> 250 | AI4: =IF(J4="SM","367","0")*K4*W4 -> 0 | AJ4: =SUM(AB4:AI4) -> 8325.94 | AM4: =L4/$Y$18*N4*$AP$3 -> 0 | AN4: =AM4*$Y$4*$AP$3 -> 0 | AO4: =SUM(AM4:AN4) -> 0 | AP4: GROSS BASE SALARY/ETAT* SICK LEAVE HOURS *20% I o 20% zmniejsza się Basic Salary Manager i Social Insurance w Manager - Target | AY4: =K4*L4*W4-BJ4 -> 6300 | AZ4: =V4 -> 0 | BA4: =(AY4+AZ4+BE4+BF4)*$Y$4-BK4 -> 1108.915 | BB4: =(AY4+AZ4+BE4+BF4)*$Y$6 -> 167.025 | BC4: =IFERROR(VLOOKUP(J4,DANE!$B$3:$H$7,5,FALSE),"0")*K4*W4 -> 300 | BD4: =K4*$Y$13*W4 -> 200 | BE4: =IFERROR(VLOOKUP(J4,DANE!$B$2:$I$7,7,FALSE),"0")*W4 -> 250 | BF4: =IF(J4="SM","367","0")*K4*W4 -> 0 | BG4: =SUM(AY4:BF4) -> 8325.94 | BJ4: =L4/$Y$18*T4*$BM$3 -> 0 | BK4: =BJ4*$Y$4*$BM$3 -> 0 | BL4: =SUM(BJ4:BK4) -> 0 | BM4: GROSS BASE SALARY/ETAT* SICK LEAVE HOURS *20% I o 20% zmniejsza się Basic Salary Manager i Social Insurance w Manager - Target
B5: MONTH | C5: WRZESIEŃ | I5: Zuzanna Makowska | J5: SSV-PM | K5: 0.75 | L5: 3510 | M5: 96 | O5: 5 | S5: 96 | U5: 5 | W5: 1 | X5: =IFERROR(IF(Q5="Tak",K5*$C$8/8*7*W5,K5*$C$8),"") -> 132 | Y5: FGŚP + Fundusz Pracy | AB5: =K5*L5*W5-AM5 -> 2632.5 | AC5: =P5 -> 0 | AD5: =(AB5+AC5+AH5+AI5)*$Y$4-AN5 -> 479.54225 | AE5: =(AB5+AC5+AH5+AI5)*$Y$6 -> 72.22875 | AF5: =(IFERROR(VLOOKUP(J5,DANE!$B$3:$H$7,5,FALSE),"0")*K5)*W5 -> 262.5 | AG5: =K5*$Y$13*W5 -> 150 | AH5: =IFERROR(VLOOKUP(J5,DANE!$B$2:$I$7,7,FALSE),"0")*W5 -> 200 | AI5: =IF(J5="SM","367","0")*K5*W5 -> 0 | AJ5: =SUM(AB5:AI5) -> 3796.771 | AM5: =L5/$Y$18*N5*$AP$3 -> 0 | AN5: =AM5*$Y$4*$AP$3 -> 0 | AO5: =SUM(AM5:AN5) -> 0 | AY5: =K5*L5*W5-BJ5 -> 2632.5 | AZ5: =V5 -> 0 | BA5: =(AY5+AZ5+BE5+BF5)*$Y$4-BK5 -> 479.54225 | BB5: =(AY5+AZ5+BE5+BF5)*$Y$6 -> 72.22875 | BC5: =IFERROR(VLOOKUP(J5,DANE!$B$3:$H$7,5,FALSE),"0")*K5*W5 -> 262.5 | BD5: =K5*$Y$13*W5 -> 150 | BE5: =IFERROR(VLOOKUP(J5,DANE!$B$2:$I$7,7,FALSE),"0")*W5 -> 200 | BF5: =IF(J5="SM","367","0")*K5*W5 -> 0 | BG5: =SUM(AY5:BF5) -> 3796.771 | BJ5: =L5/$Y$18*T5*$BM$3 -> 0 | BK5: =BJ5*$Y$4*$BM$3 -> 0 | BL5: =SUM(BJ5:BK5) -> 0
I6: Weronika Bieńkowska | J6: SSV | K6: 0.5 | L6: 5600 | M6: 88 | O6: 3 | S6: 39 | T6: 4 | U6: 3 | W6: 1 | X6: =IFERROR(IF(Q6="Tak",K6*$C$8/8*7*W6,K6*$C$8),"") -> 88 | Y6: 0.0255 | AB6: =K6*L6*W6-AM6 -> 2800 | AC6: =P6 -> 0 | AD6: =(AB6+AC6+AH6+AI6)*$Y$4-AN6 -> 507.9 | AE6: =(AB6+AC6+AH6+AI6)*$Y$6 -> 76.5 | AF6: =(IFERROR(VLOOKUP(J6,DANE!$B$3:$H$7,5,FALSE),"0")*K6)*W6 -> 175 | AG6: =K6*$Y$13*W6 -> 100 | AH6: =IFERROR(VLOOKUP(J6,DANE!$B$2:$I$7,7,FALSE),"0")*W6 -> 200 | AI6: =IF(J6="SM","367","0")*K6*W6 -> 0 | AJ6: =SUM(AB6:AI6) -> 3859.4 | AM6: =L6/$Y$18*N6*$AP$3 -> 0 | AN6: =AM6*$Y$4*$AP$3 -> 0 | AO6: =SUM(AM6:AN6) -> 0 | AY6: =K6*L6*W6-BJ6 -> 2774.5455 | AZ6: =V6 -> 0 | BA6: =(AY6+AZ6+BE6+BF6)*$Y$4-BK6 -> 502.72865 | BB6: =(AY6+AZ6+BE6+BF6)*$Y$6 -> 75.850909 | BC6: =IFERROR(VLOOKUP(J6,DANE!$B$3:$H$7,5,FALSE),"0")*K6*W6 -> 175 | BD6: =K6*$Y$13*W6 -> 100 | BE6: =IFERROR(VLOOKUP(J6,DANE!$B$2:$I$7,7,FALSE),"0")*W6 -> 200 | BF6: =IF(J6="SM","367","0")*K6*W6 -> 0 | BG6: =SUM(AY6:BF6) -> 3828.125 | BJ6: =L6/$Y$18*T6*$BM$3 -> 25.454545 | BK6: =BJ6*$Y$4*$BM$3 -> 0.86189091 | BL6: =SUM(BJ6:BK6) -> 26.316436
B7: OPEN DAYS STORE | I7: Nikola Studzińska | J7: SSV | K7: 0.5 | L7: 2300 | M7: 56 | O7: 4 | S7: 60 | U7: 4 | W7: 1 | X7: =IFERROR(IF(Q7="Tak",K7*$C$8/8*7*W7,K7*$C$8),"") -> 88 | AB7: =K7*L7*W7-AM7 -> 1150 | AC7: =P7 -> 0 | AD7: =(AB7+AC7+AH7+AI7)*$Y$4-AN7 -> 228.555 | AE7: =(AB7+AC7+AH7+AI7)*$Y$6 -> 34.425 | AF7: =(IFERROR(VLOOKUP(J7,DANE!$B$3:$H$7,5,FALSE),"0")*K7)*W7 -> 175 | AG7: =K7*$Y$13*W7 -> 100 | AH7: =IFERROR(VLOOKUP(J7,DANE!$B$2:$I$7,7,FALSE),"0")*W7 -> 200 | AI7: =IF(J7="SM","367","0")*K7*W7 -> 0 | AJ7: =SUM(AB7:AI7) -> 1887.98 | AM7: =L7/$Y$18*N7*$AP$3 -> 0 | AN7: =AM7*$Y$4*$AP$3 -> 0 | AO7: =SUM(AM7:AN7) -> 0 | AY7: =K7*L7*W7-BJ7 -> 1150 | AZ7: =V7 -> 0 | BA7: =(AY7+AZ7+BE7+BF7)*$Y$4-BK7 -> 228.555 | BB7: =(AY7+AZ7+BE7+BF7)*$Y$6 -> 34.425 | BC7: =IFERROR(VLOOKUP(J7,DANE!$B$3:$H$7,5,FALSE),"0")*K7*W7 -> 175 | BD7: =K7*$Y$13*W7 -> 100 | BE7: =IFERROR(VLOOKUP(J7,DANE!$B$2:$I$7,7,FALSE),"0")*W7 -> 200 | BF7: =IF(J7="SM","367","0")*K7*W7 -> 0 | BG7: =SUM(AY7:BF7) -> 1887.98 | BJ7: =L7/$Y$18*T7*$BM$3 -> 0 | BK7: =BJ7*$Y$4*$BM$3 -> 0 | BL7: =SUM(BJ7:BK7) -> 0
B8: FULL CONTRACT IS (IN HOURS) | C8: =IFERROR(VLOOKUP(C5,DANE!$J$3:$L$14,3,FALSE),"") -> 176 | I8: Kamil Kamiński | J8: SSV | K8: 1 | L8: 5600 | M8: 128 | O8: 6 | S8: 128 | U8: 6 | V8: 300 | W8: 1 | X8: =IFERROR(IF(Q8="Tak",K8*$C$8/8*7*W8,K8*$C$8),"") -> 176 | AB8: =K8*L8*W8-AM8 -> 5600 | AC8: =P8 -> 0 | AD8: =(AB8+AC8+AH8+AI8)*$Y$4-AN8 -> 981.94 | AE8: =(AB8+AC8+AH8+AI8)*$Y$6 -> 147.9 | AF8: =(IFERROR(VLOOKUP(J8,DANE!$B$3:$H$7,5,FALSE),"0")*K8)*W8 -> 350 | AG8: =K8*$Y$13*W8 -> 200 | AH8: =IFERROR(VLOOKUP(J8,DANE!$B$2:$I$7,7,FALSE),"0")*W8 -> 200 | AI8: =IF(J8="SM","367","0")*K8*W8 -> 0 | AJ8: =SUM(AB8:AI8) -> 7479.84 | AM8: =L8/$Y$18*N8*$AP$3 -> 0 | AN8: =AM8*$Y$4*$AP$3 -> 0 | AO8: =SUM(AM8:AN8) -> 0 | AY8: =K8*L8*W8-BJ8 -> 5600 | AZ8: =V8 -> 300 | BA8: =(AY8+AZ8+BE8+BF8)*$Y$4-BK8 -> 1032.73 | BB8: =(AY8+AZ8+BE8+BF8)*$Y$6 -> 155.55 | BC8: =IFERROR(VLOOKUP(J8,DANE!$B$3:$H$7,5,FALSE),"0")*K8*W8 -> 350 | BD8: =K8*$Y$13*W8 -> 200 | BE8: =IFERROR(VLOOKUP(J8,DANE!$B$2:$I$7,7,FALSE),"0")*W8 -> 200 | BF8: =IF(J8="SM","367","0")*K8*W8 -> 0 | BG8: =SUM(AY8:BF8) -> 7838.28 | BJ8: =L8/$Y$18*T8*$BM$3 -> 0 | BK8: =BJ8*$Y$4*$BM$3 -> 0 | BL8: =SUM(BJ8:BK8) -> 0
B9: SALES | C9: 310000 | D9: =IFERROR(VLOOKUP($B9,AOP!$A$3:$Z$100,VLOOKUP(CALCULATOR!$C$5,DANE!$B$17:$C$28,2,FALSE),FALSE),"") | E9: 280000 | W9: 1 | X9: =IFERROR(IF(Q9="Tak",K9*$C$8/8*7*W9,K9*$C$8),"") -> 0 | AB9: =K9*L9*W9-AM9 -> 0 | AC9: =P9 -> 0 | AD9: =(AB9+AC9+AH9+AI9)*$Y$4-AN9 -> 0 | AE9: =(AB9+AC9+AH9+AI9)*$Y$6 -> 0 | AF9: =(IFERROR(VLOOKUP(J9,DANE!$B$3:$H$7,5,FALSE),"0")*K9)*W9 -> 0 | AG9: =K9*$Y$13*W9 -> 0 | AH9: =IFERROR(VLOOKUP(J9,DANE!$B$2:$I$7,7,FALSE),"0")*W9 -> 0 | AI9: =IF(J9="SM","367","0")*K9*W9 -> 0 | AJ9: =SUM(AB9:AI9) -> 0 | AM9: =L9/$Y$18*N9*$AP$3 -> 0 | AN9: =AM9*$Y$4*$AP$3 -> 0 | AO9: =SUM(AM9:AN9) -> 0 | AY9: =K9*L9*W9-BJ9 -> 0 | AZ9: =V9 -> 0 | BA9: =(AY9+AZ9+BE9+BF9)*$Y$4-BK9 -> 0 | BB9: =(AY9+AZ9+BE9+BF9)*$Y$6 -> 0 | BC9: =IFERROR(VLOOKUP(J9,DANE!$B$3:$H$7,5,FALSE),"0")*K9*W9 -> 0 | BD9: =K9*$Y$13*W9 -> 0 | BE9: =IFERROR(VLOOKUP(J9,DANE!$B$2:$I$7,7,FALSE),"0")*W9 -> 0 | BF9: =IF(J9="SM","367","0")*K9*W9 -> 0 | BG9: =SUM(AY9:BF9) -> 0 | BJ9: =L9/$Y$18*T9*$BM$3 -> 0 | BK9: =BJ9*$Y$4*$BM$3 -> 0 | BL9: =SUM(BJ9:BK9) -> 0
W10: 1 | X10: =IFERROR(IF(Q10="Tak",K10*$C$8/8*7*W10,K10*$C$8),"") -> 0 | AB10: =K10*L10*W10-AM10 -> 0 | AC10: =P10 -> 0 | AD10: =(AB10+AC10+AH10+AI10)*$Y$4-AN10 -> 0 | AE10: =(AB10+AC10+AH10+AI10)*$Y$6 -> 0 | AF10: =(IFERROR(VLOOKUP(J10,DANE!$B$3:$H$7,5,FALSE),"0")*K10)*W10 -> 0 | AG10: =K10*$Y$13*W10 -> 0 | AH10: =IFERROR(VLOOKUP(J10,DANE!$B$2:$I$7,7,FALSE),"0")*W10 -> 0 | AI10: =IF(J10="SM","367","0")*K10*W10 -> 0 | AJ10: =SUM(AB10:AI10) -> 0 | AM10: =L10/$Y$18*N10*$AP$3 -> 0 | AN10: =AM10*$Y$4*$AP$3 -> 0 | AO10: =SUM(AM10:AN10) -> 0 | AY10: =K10*L10*W10-BJ10 -> 0 | AZ10: =V10 -> 0 | BA10: =(AY10+AZ10+BE10+BF10)*$Y$4-BK10 -> 0 | BB10: =(AY10+AZ10+BE10+BF10)*$Y$6 -> 0 | BC10: =IFERROR(VLOOKUP(J10,DANE!$B$3:$H$7,5,FALSE),"0")*K10*W10 -> 0 | BD10: =K10*$Y$13*W10 -> 0 | BE10: =IFERROR(VLOOKUP(J10,DANE!$B$2:$I$7,7,FALSE),"0")*W10 -> 0 | BF10: =IF(J10="SM","367","0")*K10*W10 -> 0 | BG10: =SUM(AY10:BF10) -> 0 | BJ10: =L10/$Y$18*T10*$BM$3 -> 0 | BK10: =BJ10*$Y$4*$BM$3 -> 0 | BL10: =SUM(BJ10:BK10) -> 0
B11: TRANSACTIONS | C11: 10900 | D11: =IFERROR(VLOOKUP(B11,AOP!$A$2:$Z$100,VLOOKUP(CALCULATOR!C5,DANE!B17:C28,2,FALSE),FALSE),"") | E11: 9700 | W11: 1 | X11: =IFERROR(IF(Q11="Tak",K11*$C$8/8*7*W11,K11*$C$8),"") -> 0 | AB11: =K11*L11*W11-AM11 -> 0 | AC11: =P11 -> 0 | AD11: =(AB11+AC11+AH11+AI11)*$Y$4-AN11 -> 0 | AE11: =(AB11+AC11+AH11+AI11)*$Y$6 -> 0 | AF11: =(IFERROR(VLOOKUP(J11,DANE!$B$3:$H$7,5,FALSE),"0")*K11)*W11 -> 0 | AG11: =K11*$Y$13*W11 -> 0 | AH11: =IFERROR(VLOOKUP(J11,DANE!$B$2:$I$7,7,FALSE),"0")*W11 -> 0 | AI11: =IF(J11="SM","367","0")*K11*W11 -> 0 | AJ11: =SUM(AB11:AI11) -> 0 | AM11: =L11/$Y$18*N11*$AP$3 -> 0 | AN11: =AM11*$Y$4*$AP$3 -> 0 | AO11: =SUM(AM11:AN11) -> 0 | AY11: =K11*L11*W11-BJ11 -> 0 | AZ11: =V11 -> 0 | BA11: =(AY11+AZ11+BE11+BF11)*$Y$4-BK11 -> 0 | BB11: =(AY11+AZ11+BE11+BF11)*$Y$6 -> 0 | BC11: =IFERROR(VLOOKUP(J11,DANE!$B$3:$H$7,5,FALSE),"0")*K11*W11 -> 0 | BD11: =K11*$Y$13*W11 -> 0 | BE11: =IFERROR(VLOOKUP(J11,DANE!$B$2:$I$7,7,FALSE),"0")*W11 -> 0 | BF11: =IF(J11="SM","367","0")*K11*W11 -> 0 | BG11: =SUM(AY11:BF11) -> 0 | BJ11: =L11/$Y$18*T11*$BM$3 -> 0 | BK11: =BJ11*$Y$4*$BM$3 -> 0 | BL11: =SUM(BJ11:BK11) -> 0
W12: 1 | X12: =IFERROR(IF(Q12="Tak",K12*$C$8/8*7*W12,K12*$C$8),"") -> 0 | Y12: PFRON | AB12: =K12*L12*W12-AM12 -> 0 | AC12: =P12 -> 0 | AD12: =(AB12+AC12+AH12+AI12)*$Y$4-AN12 -> 0 | AE12: =(AB12+AC12+AH12+AI12)*$Y$6 -> 0 | AF12: =(IFERROR(VLOOKUP(J12,DANE!$B$3:$H$7,5,FALSE),"0")*K12)*W12 -> 0 | AG12: =K12*$Y$13*W12 -> 0 | AH12: =IFERROR(VLOOKUP(J12,DANE!$B$2:$I$7,7,FALSE),"0")*W12 -> 0 | AI12: =IF(J12="SM","367","0")*K12*W12 -> 0 | AJ12: =SUM(AB12:AI12) -> 0 | AM12: =L12/$Y$18*N12*$AP$3 -> 0 | AN12: =AM12*$Y$4*$AP$3 -> 0 | AO12: =SUM(AM12:AN12) -> 0 | AY12: =K12*L12*W12-BJ12 -> 0 | AZ12: =V12 -> 0 | BA12: =(AY12+AZ12+BE12+BF12)*$Y$4-BK12 -> 0 | BB12: =(AY12+AZ12+BE12+BF12)*$Y$6 -> 0 | BC12: =IFERROR(VLOOKUP(J12,DANE!$B$3:$H$7,5,FALSE),"0")*K12*W12 -> 0 | BD12: =K12*$Y$13*W12 -> 0 | BE12: =IFERROR(VLOOKUP(J12,DANE!$B$2:$I$7,7,FALSE),"0")*W12 -> 0 | BF12: =IF(J12="SM","367","0")*K12*W12 -> 0 | BG12: =SUM(AY12:BF12) -> 0 | BJ12: =L12/$Y$18*T12*$BM$3 -> 0 | BK12: =BJ12*$Y$4*$BM$3 -> 0 | BL12: =SUM(BJ12:BK12) -> 0
B13: AVG DAILY OPENING HOURS | I13: Manager Maternity | Y13: 200 | AJ13: =SUM(AB13:AI13) -> 0 | BC13: =AF13 -> 0 | BE13: =AH13 -> 0 | BG13: =SUM(AY13:BF13) -> 0
B14: COL | C14: =C45 -> 78032.621 | D14: =D45 -> 0 | E14: =E45 -> 76149.551 | F14: =F45 -> 0 | I14: Manager Bench | W14: 1 | X14: =IFERROR(IF(Q14="Tak",K14*$C$8/8*7*W14,K14*$C$8),"") -> 0 | Y14: EQUIVALENT CREW | AB14: =K14*L14*W14-AM14 -> 0 | AC14: =P14 -> 0 | AD14: =(AB14+AC14+AH14+AI14)*$Y$4-AN14 -> 0 | AE14: =(AB14+AC14+AH14+AI14)*$Y$6 -> 0 | AF14: =(IFERROR(VLOOKUP(J14,DANE!$B$3:$H$7,5,FALSE),"0")*K14)*W14 -> 0 | AG14: =K14*$Y$13*W14 -> 0 | AH14: =(IFERROR(VLOOKUP(J14,DANE!$B$2:$I$7,7,FALSE),"0")*K14)*W14 -> 0 | AI14: =IF(J14="SM","367","0")*K14*W14 -> 0 | AJ14: =SUM(AB14:AI14) -> 0 | AM14: =L14/$Y$18*N14*$AP$3 -> 0 | AN14: =AM14*$Y$4*$AP$3 -> 0 | AO14: =SUM(AM14:AN14) -> 0 | AY14: =K14*L14*W14-BJ14 -> 0 | AZ14: =V14 -> 0 | BA14: =(AY14+AZ14+BE14+BF14)*$Y$4-BK14 -> 0 | BB14: =(AY14+AZ14+BE14+BF14)*$Y$6 -> 0 | BC14: =IFERROR(VLOOKUP(J14,DANE!$B$3:$H$7,5,FALSE),"0")*K14*W14 -> 0 | BD14: =K14*$Y$13*W14 -> 0 | BE14: =(IFERROR(VLOOKUP(J14,DANE!$B$2:$I$7,7,FALSE),"0")*K14)*W14 -> 0 | BF14: =IF(J14="SM","367","0")*K14*W14 -> 0 | BG14: =SUM(AY14:BF14) -> 0 | BJ14: =L14/$Y$18*T14*$BM$3 -> 0 | BK14: =BJ14*$Y$4*$BM$3 -> 0 | BL14: =SUM(BJ14:BK14) -> 0
I15: DM costs | P15: 685 | AC15: =P15 -> 685 | AD15: =P15*$Y$4 -> 115.9705 | AJ15: =SUM(AB15:AI15) -> 800.9705 | AZ15: =AC15 -> 685 | BA15: =AZ15*$Y$4 -> 115.9705 | BG15: =SUM(AY15:BF15) -> 800.9705
B16: COL% | C16: =IFERROR(C14/C9,"-") -> 0.25171813 | D16: =IFERROR(D14/D9,"-") -> - | E16: =IFERROR(E14/E9,"-") -> 0.27196268 | F16: =IFERROR(F14/F9,"-") -> - | I16: DOS+ accrual | Y16: =DANE!F9 -> 0.85 | AC16: =P16 -> 0 | AD16: =P16*$Y$4 -> 0 | AJ16: =SUM(AB16:AI16) -> 0 | AZ16: =AC16 -> 0 | BA16: =AZ16*$Y$4 -> 0 | BG16: =SUM(AY16:BF16) -> 0
I17: Holiday accrual | L17: ='Rezerwa urlopowa'!G106 -> 3454 | V17: 1819 | Y17: ETAT | AB17: =L17 -> 3454 | AJ17: =SUM(AB17:AI17) -> 3454 | AY17: =V17 -> 1819 | BG17: =SUM(AY17:BF17) -> 1819
B18: FIXED COL | C18: =IFERROR(C47+C48+C49+C56+C57+C60+C63+C62+C64+C66+C50+C51+C52,"") -> 44608.359 | D18: =IFERROR(D47+D48+D49+D56+D57+D60+D63+D62+D64+D66+D50+D51+D52,"") -> 0 | E18: =IFERROR(E47+E48+E49+E56+E57+E60+E63+E62+E64+E66+E50+E51+E52,"") -> 42892.713 | F18: =IFERROR(F47+F48+F49+F56+F57+F60+F63+F62+F64+F66+F50+F51+F52,"") -> 0 | H18: MANAGER TOTAL: | K18: =SUM(K3:K12) -> 4.75 | M18: =SUM(M3:M17) -> 720 | N18: =SUM(N3:N17) -> 0 | O18: =SUM(O3:O17) -> 18 | P18: =SUM(P3:P17)-P19 -> 685 | S18: =SUM(S3:S17) -> 675 | T18: =SUM(T3:T17) -> 4 | U18: =SUM(U3:U17) -> 18 | V18: =SUM(V3:V16)-V19 -> 0 | Y18: =VLOOKUP(CALCULATOR!$C$5,DANE!J3:L14,3,FALSE) -> 176 | AB18: =SUM(AB3:AB17)-AD17 -> 29136.5 | AC18: =SUM(AC3:AC17)-AC19 -> 685 | AD18: =SUM(AD3:AD17) -> 4754.7059 | AE18: =SUM(AE3:AE17) -> 698.68725 | AF18: =SUM(AF3:AF17) -> 1562.5 | AG18: =SUM(AG3:AG17) -> 950 | AH18: =SUM(AH3:AH17) -> 1350 | AI18: =SUM(AI3:AI17) -> 367 | AJ18: =SUM(AJ3:AJ17) -> 39504.393 | AM18: =SUM(AM3:AM17) -> 0 | AN18: =SUM(AN3:AN17) -> 0 | AO18: =SUM(AO3:AO17) -> 0 | AY18: =SUM(AY3:AY17)-BA17 -> 27476.045 | AZ18: =SUM(AZ3:AZ17)-AZ19 -> 685 | BA18: =SUM(BA3:BA17) -> 4800.3245 | BB18: =SUM(BB3:BB17) -> 705.68816 | BC18: =SUM(BC3:BC17) -> 1562.5 | BD18: =SUM(BD3:BD17) -> 950 | BE18: =SUM(BE3:BE17) -> 1350 | BF18: =SUM(BF3:BF17) -> 367 | BG18: =SUM(BG3:BG17) -> 38196.558 | BJ18: =SUM(BJ3:BJ17) -> 25.454545 | BK18: =SUM(BK3:BK17) -> 0.86189091 | BL18: =SUM(BL3:BL17) -> 26.316436
P19: =SUMIF($J$3:$J$12,"SSV",P3:P12) -> 0 | V19: =SUMIF($J$3:$J$12,"SSV",V3:V12) -> 300 | AC19: =SUMIF($J$3:$J$12,"SSV",AC3:AC12) -> 0 | AZ19: =SUMIF($J$3:$J$12,"SSV",AZ3:AZ12) -> 300
H20: UMOWA O PRACĘ - TARGET | I20: Imię i Nazwisko | J20: Stanowisko | K20: Wymiar etatu | L20: Stawka brutto | M20: Planowany czas pracy | N20: Zwolnienie lekarskie | O20: Urlop | P20: Etat | Q20: ON | R20: UMOWA O PRACĘ - ESTIMATION | S20: Rzeczywisty czas pracy | T20: Zwolnienie lekarskie | U20: Urlop | V20: Bonus | W20: ALERT: | Y20: Hourly Job - Barista | AA20: UMOWA O PRACĘ - TARGET | AB20: Basic salary crew | AD20: Social insurance: | AE20: FGŚP + Fundusz Pracy | AF20: Equivalent | AG20: PFRON: | AJ20: COL TOTAL | AL20: UMOWA O PRACĘ - PLAN - SICK LEAVE | AM20: Basic salary crew | AN20: Social insurance: | AO20: COL TOTAL | AP20: Sick Leave Salary | AR20: UMOWA O PRACĘ - HOLIDAY - TARGET | AS20: Basic salary crew | AT20: Social insurance: | AU20: Equivalent | AV20: COL TOTAL | AX20: UMOWA O PRACĘ - ESTIMATION | AY20: Basic salary crew | BA20: Social insurance: | BB20: FGŚP + Fundusz Pracy | BC20: Equivalent | BD20: PFRON: | BG20: COL TOTAL | BI20: UMOWA O PRACĘ - ESTIMATION - SICK LEAVE | BJ20: Basic salary crew | BK20: Social insurance: | BL20: COL TOTAL | BM20: Sick Leave Salary | BO20: UMOWA O PRACĘ - HOLIDAY - ESTIMATION | BP20: Basic salary crew | BQ20: Social insurance: | BR20: Equivalent | BS20: COL TOTAL
B21: MANAGER WORKING HOURS | C21: =M18 -> 720 | E21: =S18 -> 675
B22: CREW WORKING HOURS | C22: =IFERROR(M41+M66,"") -> 1040 | E22: =S41+S66 -> 1038.5 | I22: Hanna Domachowska | J22: BT | K22: 0.5 | L22: 31.4 | M22: 88 | P22: =IFERROR(IF(Q22="tak",$C$8/8*7*K22,K22*$C$8),"") -> 88 | S22: 85 | W22: =IF(AND(SUM(M22:O22)<P22,(SUM(M22:O22)>0)),"TARGET: NIEDOGODZINY",IF(SUM(M22:O22)>P22,"TARGET: NADGODZINY",IF(AND(SUM(S22:U22)<P22,(SUM(S22:U22)>0)),"ESTIMATION: NIEDOGODZINY",IF(SUM(S22:U22)>P22,"ESTIMATION: NADGODZINY","-")))) -> ESTIMATION: NIEDOGODZINY | Y22: =IF(OR(J22="KP",J22="BT",J22="LOBBY",J22="B"),(L22*1.1948)+0.7,"-") -> 38.21672 | AB22: =IF(L22<VLOOKUP($C$5,DANE!$J$3:$N$14,4,FALSE),VLOOKUP($C$5,DANE!$J$3:$N$14,4,FALSE)*M22,L22*M22) -> 2763.2 | AD22: =AB22*$Y$4 -> 467.80976 | AE22: =AB22*$Y$6 -> 70.4616 | AF22: =M22*$Y$16 -> 74.8 | AG22: =K22*$Y$13 -> 100 | AJ22: =SUM(AB22:AG22) -> 3476.2714 | AM22: =N22*IF(L22<VLOOKUP($C$5,DANE!$J$3:$N$14,4,FALSE),VLOOKUP($C$5,DANE!$J$3:$N$14,4,FALSE),L22)*$AP$22 -> 0 | AN22: =AM22*$Y$4*$AP$22 -> 0 | AO22: =SUM(AM22:AN22) -> 0 | AP22: 0.8 | AS22: =O22*IF(L22<VLOOKUP($C$5,DANE!$J$3:$N$14,4,FALSE),VLOOKUP($C$5,DANE!$J$3:$N$14,4,FALSE),L22) -> 0 | AT22: =AS22*$Y$4 -> 0 | AU22: =O22*$Y$16 -> 0 | AV22: =SUM(AS22:AT22) -> 0 | AY22: =IF(L22<VLOOKUP($C$5,DANE!$J$3:$N$14,4,FALSE),VLOOKUP($C$5,DANE!$J$3:$N$14,4,FALSE)*S22,L22*S22) -> 2669 | BA22: =AY22*$Y$4 -> 451.8617 | BB22: =AY22*$Y$6 -> 68.0595 | BC22: =S22*$Y$16 -> 72.25 | BD22: =K22*$Y$13 -> 100 | BG22: =SUM(AY22:BD22) -> 3361.1712 | BJ22: =T22*IF(L22<VLOOKUP($C$5,DANE!$J$3:$N$14,4,FALSE),VLOOKUP($C$5,DANE!$J$3:$N$14,4,FALSE),L22)*$BM$22 -> 0 | BK22: =BJ22*$Y$4*$BM$22 -> 0 | BL22: =SUM(BJ22:BK22) -> 0 | BM22: 0.8 | BP22: =U22*IF(L22<VLOOKUP($C$5,DANE!$J$3:$N$14,4,FALSE),VLOOKUP($C$5,DANE!$J$3:$N$14,4,FALSE),L22) -> 0 | BQ22: =BP22*$Y$4 -> 0 | BR22: =U22*$Y$16 -> 0 | BS22: =SUM(BP22:BQ22) -> 0
B23: TPLH (Total) | C23: =IFERROR(C11/C36,"-") -> 6.1931818 | E23: =IFERROR(E11/E36,"-") -> 5.6609279 | F23: =IFERROR(F11/F36,"-") -> - | I23: Gabriela Znojek | J23: B | K23: 0.75 | L23: 30.75 | M23: 132 | P23: =IFERROR(IF(Q23="tak",$C$8/8*7*K23,K23*$C$8),"") -> 132 | S23: 120 | W23: =IF(AND(SUM(M23:O23)<P23,(SUM(M23:O23)>0)),"TARGET: NIEDOGODZINY",IF(SUM(M23:O23)>P23,"TARGET: NADGODZINY",IF(AND(SUM(S23:U23)<P23,(SUM(S23:U23)>0)),"ESTIMATION: NIEDOGODZINY",IF(SUM(S23:U23)>P23,"ESTIMATION: NADGODZINY","-")))) -> ESTIMATION: NIEDOGODZINY | Y23: =IF(OR(J23="KP",J23="BT",J23="LOBBY",J23="B"),(L23*1.1948)+0.7,"-") -> 37.4401 | AB23: =IF(L23<VLOOKUP($C$5,DANE!$J$3:$N$14,4,FALSE),VLOOKUP($C$5,DANE!$J$3:$N$14,4,FALSE)*M23,L23*M23) -> 4059 | AD23: =AB23*$Y$4 -> 687.1887 | AE23: =AB23*$Y$6 -> 103.5045 | AF23: =M23*$Y$16 -> 112.2 | AG23: =K23*$Y$13 -> 150 | AJ23: =SUM(AB23:AG23) -> 5111.8932 | AM23: =N23*IF(L23<VLOOKUP($C$5,DANE!$J$3:$N$14,4,FALSE),VLOOKUP($C$5,DANE!$J$3:$N$14,4,FALSE),L23)*$AP$22 -> 0 | AN23: =AM23*$Y$4*$AP$22 -> 0 | AO23: =SUM(AM23:AN23) -> 0 | AS23: =O23*IF(L23<VLOOKUP($C$5,DANE!$J$3:$N$14,4,FALSE),VLOOKUP($C$5,DANE!$J$3:$N$14,4,FALSE),L23) -> 0 | AT23: =AS23*$Y$4 -> 0 | AU23: =O23*$Y$16 -> 0 | AV23: =SUM(AS23:AT23) -> 0 | AY23: =IF(L23<VLOOKUP($C$5,DANE!$J$3:$N$14,4,FALSE),VLOOKUP($C$5,DANE!$J$3:$N$14,4,FALSE)*S23,L23*S23) -> 3690 | BA23: =AY23*$Y$4 -> 624.717 | BB23: =AY23*$Y$6 -> 94.095 | BC23: =S23*$Y$16 -> 102 | BD23: =K23*$Y$13 -> 150 | BG23: =SUM(AY23:BD23) -> 4660.812 | BJ23: =T23*IF(L23<VLOOKUP($C$5,DANE!$J$3:$N$14,4,FALSE),VLOOKUP($C$5,DANE!$J$3:$N$14,4,FALSE),L23)*$BM$22 -> 0 | BK23: =BJ23*$Y$4*$BM$22 -> 0 | BL23: =SUM(BJ23:BK23) -> 0 | BP23: =U23*IF(L23<VLOOKUP($C$5,DANE!$J$3:$N$14,4,FALSE),VLOOKUP($C$5,DANE!$J$3:$N$14,4,FALSE),L23) -> 0 | BQ23: =BP23*$Y$4 -> 0 | BR23: =U23*$Y$16 -> 0 | BS23: =SUM(BP23:BQ23) -> 0
B24: TPLH (Coverage) | C24: =IFERROR(C11/(C36-C27-C30),"-") -> 6.4688427 | E24: =IFERROR(E11/(E36-E27-E30),"-") -> 5.6609279 | F24: =IFERROR(F11/(F36-F27-F30),"-") -> - | P24: =IFERROR(IF(Q24="tak",$C$8/8*7*K24,K24*$C$8),"") -> 0 | W24: =IF(AND(SUM(M24:O24)<P24,(SUM(M24:O24)>0)),"TARGET: NIEDOGODZINY",IF(SUM(M24:O24)>P24,"TARGET: NADGODZINY",IF(AND(SUM(S24:U24)<P24,(SUM(S24:U24)>0)),"ESTIMATION: NIEDOGODZINY",IF(SUM(S24:U24)>P24,"ESTIMATION: NADGODZINY","-")))) -> - | Y24: =IF(OR(J24="KP",J24="BT",J24="LOBBY",J24="B"),(L24*1.1948)+0.7,"-") -> - | AB24: =IF(L24<VLOOKUP($C$5,DANE!$J$3:$N$14,4,FALSE),VLOOKUP($C$5,DANE!$J$3:$N$14,4,FALSE)*M24,L24*M24) -> 0 | AD24: =AB24*$Y$4 -> 0 | AE24: =AB24*$Y$6 -> 0 | AF24: =M24*$Y$16 -> 0 | AG24: =K24*$Y$13 -> 0 | AJ24: =SUM(AB24:AG24) -> 0 | AM24: =N24*IF(L24<VLOOKUP($C$5,DANE!$J$3:$N$14,4,FALSE),VLOOKUP($C$5,DANE!$J$3:$N$14,4,FALSE),L24)*$AP$22 -> 0 | AN24: =AM24*$Y$4*$AP$22 -> 0 | AO24: =SUM(AM24:AN24) -> 0 | AS24: =O24*IF(L24<VLOOKUP($C$5,DANE!$J$3:$N$14,4,FALSE),VLOOKUP($C$5,DANE!$J$3:$N$14,4,FALSE),L24) -> 0 | AT24: =AS24*$Y$4 -> 0 | AU24: =O24*$Y$16 -> 0 | AV24: =SUM(AS24:AT24) -> 0 | AY24: =IF(L24<VLOOKUP($C$5,DANE!$J$3:$N$14,4,FALSE),VLOOKUP($C$5,DANE!$J$3:$N$14,4,FALSE)*S24,L24*S24) -> 0 | BA24: =AY24*$Y$4 -> 0 | BB24: =AY24*$Y$6 -> 0 | BC24: =S24*$Y$16 -> 0 | BD24: =K24*$Y$13 -> 0 | BG24: =SUM(AY24:BD24) -> 0 | BJ24: =T24*IF(L24<VLOOKUP($C$5,DANE!$J$3:$N$14,4,FALSE),VLOOKUP($C$5,DANE!$J$3:$N$14,4,FALSE),L24)*$BM$22 -> 0 | BK24: =BJ24*$Y$4*$BM$22 -> 0 | BL24: =SUM(BJ24:BK24) -> 0 | BP24: =U24*IF(L24<VLOOKUP($C$5,DANE!$J$3:$N$14,4,FALSE),VLOOKUP($C$5,DANE!$J$3:$N$14,4,FALSE),L24) -> 0 | BQ24: =BP24*$Y$4 -> 0 | BR24: =U24*$Y$16 -> 0 | BS24: =SUM(BP24:BQ24) -> 0
B25: TOTAL CONTRACTS | C25: =IFERROR(K18+K41+K66,"") -> 10.659091 | E25: =IFERROR(K18+K41+K66,"") -> 10.659091 | P25: =IFERROR(IF(Q25="tak",$C$8/8*7*K25,K25*$C$8),"") -> 0 | W25: =IF(AND(SUM(M25:O25)<P25,(SUM(M25:O25)>0)),"TARGET: NIEDOGODZINY",IF(SUM(M25:O25)>P25,"TARGET: NADGODZINY",IF(AND(SUM(S25:U25)<P25,(SUM(S25:U25)>0)),"ESTIMATION: NIEDOGODZINY",IF(SUM(S25:U25)>P25,"ESTIMATION: NADGODZINY","-")))) -> - | Y25: =IF(OR(J25="KP",J25="BT",J25="LOBBY",J25="B"),(L25*1.1948)+0.7,"-") -> - | AB25: =IF(L25<VLOOKUP($C$5,DANE!$J$3:$N$14,4,FALSE),VLOOKUP($C$5,DANE!$J$3:$N$14,4,FALSE)*M25,L25*M25) -> 0 | AD25: =AB25*$Y$4 -> 0 | AE25: =AB25*$Y$6 -> 0 | AF25: =M25*$Y$16 -> 0 | AG25: =K25*$Y$13 -> 0 | AJ25: =SUM(AB25:AG25) -> 0 | AM25: =N25*IF(L25<VLOOKUP($C$5,DANE!$J$3:$N$14,4,FALSE),VLOOKUP($C$5,DANE!$J$3:$N$14,4,FALSE),L25)*$AP$22 -> 0 | AN25: =AM25*$Y$4*$AP$22 -> 0 | AO25: =SUM(AM25:AN25) -> 0 | AS25: =O25*IF(L25<VLOOKUP($C$5,DANE!$J$3:$N$14,4,FALSE),VLOOKUP($C$5,DANE!$J$3:$N$14,4,FALSE),L25) -> 0 | AT25: =AS25*$Y$4 -> 0 | AU25: =O25*$Y$16 -> 0 | AV25: =SUM(AS25:AT25) -> 0 | AY25: =IF(L25<VLOOKUP($C$5,DANE!$J$3:$N$14,4,FALSE),VLOOKUP($C$5,DANE!$J$3:$N$14,4,FALSE)*S25,L25*S25) -> 0 | BA25: =AY25*$Y$4 -> 0 | BB25: =AY25*$Y$6 -> 0 | BC25: =S25*$Y$16 -> 0 | BD25: =K25*$Y$13 -> 0 | BG25: =SUM(AY25:BD25) -> 0 | BJ25: =T25*IF(L25<VLOOKUP($C$5,DANE!$J$3:$N$14,4,FALSE),VLOOKUP($C$5,DANE!$J$3:$N$14,4,FALSE),L25)*$BM$22 -> 0 | BK25: =BJ25*$Y$4*$BM$22 -> 0 | BL25: =SUM(BJ25:BK25) -> 0 | BP25: =U25*IF(L25<VLOOKUP($C$5,DANE!$J$3:$N$14,4,FALSE),VLOOKUP($C$5,DANE!$J$3:$N$14,4,FALSE),L25) -> 0 | BQ25: =BP25*$Y$4 -> 0 | BR25: =U25*$Y$16 -> 0 | BS25: =SUM(BP25:BQ25) -> 0
P26: =IFERROR(IF(Q26="tak",$C$8/8*7*K26,K26*$C$8),"") -> 0 | W26: =IF(AND(SUM(M26:O26)<P26,(SUM(M26:O26)>0)),"TARGET: NIEDOGODZINY",IF(SUM(M26:O26)>P26,"TARGET: NADGODZINY",IF(AND(SUM(S26:U26)<P26,(SUM(S26:U26)>0)),"ESTIMATION: NIEDOGODZINY",IF(SUM(S26:U26)>P26,"ESTIMATION: NADGODZINY","-")))) -> - | Y26: =IF(OR(J26="KP",J26="BT",J26="LOBBY",J26="B"),(L26*1.1948)+0.7,"-") -> - | AB26: =IF(L26<VLOOKUP($C$5,DANE!$J$3:$N$14,4,FALSE),VLOOKUP($C$5,DANE!$J$3:$N$14,4,FALSE)*M26,L26*M26) -> 0 | AD26: =AB26*$Y$4 -> 0 | AE26: =AB26*$Y$6 -> 0 | AF26: =M26*$Y$16 -> 0 | AG26: =K26*$Y$13 -> 0 | AJ26: =SUM(AB26:AG26) -> 0 | AM26: =N26*IF(L26<VLOOKUP($C$5,DANE!$J$3:$N$14,4,FALSE),VLOOKUP($C$5,DANE!$J$3:$N$14,4,FALSE),L26)*$AP$22 -> 0 | AN26: =AM26*$Y$4*$AP$22 -> 0 | AO26: =SUM(AM26:AN26) -> 0 | AS26: =O26*IF(L26<VLOOKUP($C$5,DANE!$J$3:$N$14,4,FALSE),VLOOKUP($C$5,DANE!$J$3:$N$14,4,FALSE),L26) -> 0 | AT26: =AS26*$Y$4 -> 0 | AU26: =O26*$Y$16 -> 0 | AV26: =SUM(AS26:AT26) -> 0 | AY26: =IF(L26<VLOOKUP($C$5,DANE!$J$3:$N$14,4,FALSE),VLOOKUP($C$5,DANE!$J$3:$N$14,4,FALSE)*S26,L26*S26) -> 0 | BA26: =AY26*$Y$4 -> 0 | BB26: =AY26*$Y$6 -> 0 | BC26: =S26*$Y$16 -> 0 | BD26: =K26*$Y$13 -> 0 | BG26: =SUM(AY26:BD26) -> 0 | BJ26: =T26*IF(L26<VLOOKUP($C$5,DANE!$J$3:$N$14,4,FALSE),VLOOKUP($C$5,DANE!$J$3:$N$14,4,FALSE),L26)*$BM$22 -> 0 | BK26: =BJ26*$Y$4*$BM$22 -> 0 | BL26: =SUM(BJ26:BK26) -> 0 | BP26: =U26*IF(L26<VLOOKUP($C$5,DANE!$J$3:$N$14,4,FALSE),VLOOKUP($C$5,DANE!$J$3:$N$14,4,FALSE),L26) -> 0 | BQ26: =BP26*$Y$4 -> 0 | BR26: =U26*$Y$16 -> 0 | BS26: =SUM(BP26:BQ26) -> 0
B27: NON COVERAGE | P27: =IFERROR(IF(Q27="tak",$C$8/8*7*K27,K27*$C$8),"") -> 0 | W27: =IF(AND(SUM(M27:O27)<P27,(SUM(M27:O27)>0)),"TARGET: NIEDOGODZINY",IF(SUM(M27:O27)>P27,"TARGET: NADGODZINY",IF(AND(SUM(S27:U27)<P27,(SUM(S27:U27)>0)),"ESTIMATION: NIEDOGODZINY",IF(SUM(S27:U27)>P27,"ESTIMATION: NADGODZINY","-")))) -> - | Y27: =IF(OR(J27="KP",J27="BT",J27="LOBBY",J27="B"),(L27*1.1948)+0.7,"-") -> - | AB27: =IF(L27<VLOOKUP($C$5,DANE!$J$3:$N$14,4,FALSE),VLOOKUP($C$5,DANE!$J$3:$N$14,4,FALSE)*M27,L27*M27) -> 0 | AD27: =AB27*$Y$4 -> 0 | AE27: =AB27*$Y$6 -> 0 | AF27: =M27*$Y$16 -> 0 | AG27: =K27*$Y$13 -> 0 | AJ27: =SUM(AB27:AG27) -> 0 | AM27: =N27*IF(L27<VLOOKUP($C$5,DANE!$J$3:$N$14,4,FALSE),VLOOKUP($C$5,DANE!$J$3:$N$14,4,FALSE),L27)*$AP$22 -> 0 | AN27: =AM27*$Y$4*$AP$22 -> 0 | AO27: =SUM(AM27:AN27) -> 0 | AS27: =O27*IF(L27<VLOOKUP($C$5,DANE!$J$3:$N$14,4,FALSE),VLOOKUP($C$5,DANE!$J$3:$N$14,4,FALSE),L27) -> 0 | AT27: =AS27*$Y$4 -> 0 | AU27: =O27*$Y$16 -> 0 | AV27: =SUM(AS27:AT27) -> 0 | AY27: =IF(L27<VLOOKUP($C$5,DANE!$J$3:$N$14,4,FALSE),VLOOKUP($C$5,DANE!$J$3:$N$14,4,FALSE)*S27,L27*S27) -> 0 | BA27: =AY27*$Y$4 -> 0 | BB27: =AY27*$Y$6 -> 0 | BC27: =S27*$Y$16 -> 0 | BD27: =K27*$Y$13 -> 0 | BG27: =SUM(AY27:BD27) -> 0 | BJ27: =T27*IF(L27<VLOOKUP($C$5,DANE!$J$3:$N$14,4,FALSE),VLOOKUP($C$5,DANE!$J$3:$N$14,4,FALSE),L27)*$BM$22 -> 0 | BK27: =BJ27*$Y$4*$BM$22 -> 0 | BL27: =SUM(BJ27:BK27) -> 0 | BP27: =U27*IF(L27<VLOOKUP($C$5,DANE!$J$3:$N$14,4,FALSE),VLOOKUP($C$5,DANE!$J$3:$N$14,4,FALSE),L27) -> 0 | BQ27: =BP27*$Y$4 -> 0 | BR27: =U27*$Y$16 -> 0 | BS27: =SUM(BP27:BQ27) -> 0
B28: HOLIDAY | C28: =O18+O41 -> 18 | E28: =U18+U41 -> 18 | P28: =IFERROR(IF(Q28="tak",$C$8/8*7*K28,K28*$C$8),"") -> 0 | W28: =IF(AND(SUM(M28:O28)<P28,(SUM(M28:O28)>0)),"TARGET: NIEDOGODZINY",IF(SUM(M28:O28)>P28,"TARGET: NADGODZINY",IF(AND(SUM(S28:U28)<P28,(SUM(S28:U28)>0)),"ESTIMATION: NIEDOGODZINY",IF(SUM(S28:U28)>P28,"ESTIMATION: NADGODZINY","-")))) -> - | Y28: =IF(OR(J28="KP",J28="BT",J28="LOBBY",J28="B"),(L28*1.1948)+0.7,"-") -> - | AB28: =IF(L28<VLOOKUP($C$5,DANE!$J$3:$N$14,4,FALSE),VLOOKUP($C$5,DANE!$J$3:$N$14,4,FALSE)*M28,L28*M28) -> 0 | AD28: =AB28*$Y$4 -> 0 | AE28: =AB28*$Y$6 -> 0 | AF28: =M28*$Y$16 -> 0 | AG28: =K28*$Y$13 -> 0 | AJ28: =SUM(AB28:AG28) -> 0 | AM28: =N28*IF(L28<VLOOKUP($C$5,DANE!$J$3:$N$14,4,FALSE),VLOOKUP($C$5,DANE!$J$3:$N$14,4,FALSE),L28)*$AP$22 -> 0 | AN28: =AM28*$Y$4*$AP$22 -> 0 | AO28: =SUM(AM28:AN28) -> 0 | AS28: =O28*IF(L28<VLOOKUP($C$5,DANE!$J$3:$N$14,4,FALSE),VLOOKUP($C$5,DANE!$J$3:$N$14,4,FALSE),L28) -> 0 | AT28: =AS28*$Y$4 -> 0 | AU28: =O28*$Y$16 -> 0 | AV28: =SUM(AS28:AT28) -> 0 | AY28: =IF(L28<VLOOKUP($C$5,DANE!$J$3:$N$14,4,FALSE),VLOOKUP($C$5,DANE!$J$3:$N$14,4,FALSE)*S28,L28*S28) -> 0 | BA28: =AY28*$Y$4 -> 0 | BB28: =AY28*$Y$6 -> 0 | BC28: =S28*$Y$16 -> 0 | BD28: =K28*$Y$13 -> 0 | BG28: =SUM(AY28:BD28) -> 0 | BJ28: =T28*IF(L28<VLOOKUP($C$5,DANE!$J$3:$N$14,4,FALSE),VLOOKUP($C$5,DANE!$J$3:$N$14,4,FALSE),L28)*$BM$22 -> 0 | BK28: =BJ28*$Y$4*$BM$22 -> 0 | BL28: =SUM(BJ28:BK28) -> 0 | BP28: =U28*IF(L28<VLOOKUP($C$5,DANE!$J$3:$N$14,4,FALSE),VLOOKUP($C$5,DANE!$J$3:$N$14,4,FALSE),L28) -> 0 | BQ28: =BP28*$Y$4 -> 0 | BR28: =U28*$Y$16 -> 0 | BS28: =SUM(BP28:BQ28) -> 0
B29: SICK LEAVE | C29: =N18+N41 -> 0 | E29: =T18+T41 -> 4 | P29: =IFERROR(IF(Q29="tak",$C$8/8*7*K29,K29*$C$8),"") -> 0 | W29: =IF(AND(SUM(M29:O29)<P29,(SUM(M29:O29)>0)),"TARGET: NIEDOGODZINY",IF(SUM(M29:O29)>P29,"TARGET: NADGODZINY",IF(AND(SUM(S29:U29)<P29,(SUM(S29:U29)>0)),"ESTIMATION: NIEDOGODZINY",IF(SUM(S29:U29)>P29,"ESTIMATION: NADGODZINY","-")))) -> - | Y29: =IF(OR(J29="KP",J29="BT",J29="LOBBY",J29="B"),(L29*1.1948)+0.7,"-") -> - | AB29: =IF(L29<VLOOKUP($C$5,DANE!$J$3:$N$14,4,FALSE),VLOOKUP($C$5,DANE!$J$3:$N$14,4,FALSE)*M29,L29*M29) -> 0 | AD29: =AB29*$Y$4 -> 0 | AE29: =AB29*$Y$6 -> 0 | AF29: =M29*$Y$16 -> 0 | AG29: =K29*$Y$13 -> 0 | AJ29: =SUM(AB29:AG29) -> 0 | AM29: =N29*IF(L29<VLOOKUP($C$5,DANE!$J$3:$N$14,4,FALSE),VLOOKUP($C$5,DANE!$J$3:$N$14,4,FALSE),L29)*$AP$22 -> 0 | AN29: =AM29*$Y$4*$AP$22 -> 0 | AO29: =SUM(AM29:AN29) -> 0 | AS29: =O29*IF(L29<VLOOKUP($C$5,DANE!$J$3:$N$14,4,FALSE),VLOOKUP($C$5,DANE!$J$3:$N$14,4,FALSE),L29) -> 0 | AT29: =AS29*$Y$4 -> 0 | AU29: =O29*$Y$16 -> 0 | AV29: =SUM(AS29:AT29) -> 0 | AY29: =IF(L29<VLOOKUP($C$5,DANE!$J$3:$N$14,4,FALSE),VLOOKUP($C$5,DANE!$J$3:$N$14,4,FALSE)*S29,L29*S29) -> 0 | BA29: =AY29*$Y$4 -> 0 | BB29: =AY29*$Y$6 -> 0 | BC29: =S29*$Y$16 -> 0 | BD29: =K29*$Y$13 -> 0 | BG29: =SUM(AY29:BD29) -> 0 | BJ29: =T29*IF(L29<VLOOKUP($C$5,DANE!$J$3:$N$14,4,FALSE),VLOOKUP($C$5,DANE!$J$3:$N$14,4,FALSE),L29)*$BM$22 -> 0 | BK29: =BJ29*$Y$4*$BM$22 -> 0 | BL29: =SUM(BJ29:BK29) -> 0 | BP29: =U29*IF(L29<VLOOKUP($C$5,DANE!$J$3:$N$14,4,FALSE),VLOOKUP($C$5,DANE!$J$3:$N$14,4,FALSE),L29) -> 0 | BQ29: =BP29*$Y$4 -> 0 | BR29: =U29*$Y$16 -> 0 | BS29: =SUM(BP29:BQ29) -> 0
B30: TRAINING | C30: 75 | P30: =IFERROR(IF(Q30="tak",$C$8/8*7*K30,K30*$C$8),"") -> 0 | W30: =IF(AND(SUM(M30:O30)<P30,(SUM(M30:O30)>0)),"TARGET: NIEDOGODZINY",IF(SUM(M30:O30)>P30,"TARGET: NADGODZINY",IF(AND(SUM(S30:U30)<P30,(SUM(S30:U30)>0)),"ESTIMATION: NIEDOGODZINY",IF(SUM(S30:U30)>P30,"ESTIMATION: NADGODZINY","-")))) -> - | Y30: =IF(OR(J30="KP",J30="BT",J30="LOBBY",J30="B"),(L30*1.1948)+0.7,"-") -> - | AB30: =IF(L30<VLOOKUP($C$5,DANE!$J$3:$N$14,4,FALSE),VLOOKUP($C$5,DANE!$J$3:$N$14,4,FALSE)*M30,L30*M30) -> 0 | AD30: =AB30*$Y$4 -> 0 | AE30: =AB30*$Y$6 -> 0 | AF30: =M30*$Y$16 -> 0 | AG30: =K30*$Y$13 -> 0 | AJ30: =SUM(AB30:AG30) -> 0 | AM30: =N30*IF(L30<VLOOKUP($C$5,DANE!$J$3:$N$14,4,FALSE),VLOOKUP($C$5,DANE!$J$3:$N$14,4,FALSE),L30)*$AP$22 -> 0 | AN30: =AM30*$Y$4*$AP$22 -> 0 | AO30: =SUM(AM30:AN30) -> 0 | AS30: =O30*IF(L30<VLOOKUP($C$5,DANE!$J$3:$N$14,4,FALSE),VLOOKUP($C$5,DANE!$J$3:$N$14,4,FALSE),L30) -> 0 | AT30: =AS30*$Y$4 -> 0 | AU30: =O30*$Y$16 -> 0 | AV30: =SUM(AS30:AT30) -> 0 | AY30: =IF(L30<VLOOKUP($C$5,DANE!$J$3:$N$14,4,FALSE),VLOOKUP($C$5,DANE!$J$3:$N$14,4,FALSE)*S30,L30*S30) -> 0 | BA30: =AY30*$Y$4 -> 0 | BB30: =AY30*$Y$6 -> 0 | BC30: =S30*$Y$16 -> 0 | BD30: =K30*$Y$13 -> 0 | BG30: =SUM(AY30:BD30) -> 0 | BJ30: =T30*IF(L30<VLOOKUP($C$5,DANE!$J$3:$N$14,4,FALSE),VLOOKUP($C$5,DANE!$J$3:$N$14,4,FALSE),L30)*$BM$22 -> 0 | BK30: =BJ30*$Y$4*$BM$22 -> 0 | BL30: =SUM(BJ30:BK30) -> 0 | BP30: =U30*IF(L30<VLOOKUP($C$5,DANE!$J$3:$N$14,4,FALSE),VLOOKUP($C$5,DANE!$J$3:$N$14,4,FALSE),L30) -> 0 | BQ30: =BP30*$Y$4 -> 0 | BR30: =U30*$Y$16 -> 0 | BS30: =SUM(BP30:BQ30) -> 0
P31: =IFERROR(IF(Q31="tak",$C$8/8*7*K31,K31*$C$8),"") -> 0 | W31: =IF(AND(SUM(M31:O31)<P31,(SUM(M31:O31)>0)),"TARGET: NIEDOGODZINY",IF(SUM(M31:O31)>P31,"TARGET: NADGODZINY",IF(AND(SUM(S31:U31)<P31,(SUM(S31:U31)>0)),"ESTIMATION: NIEDOGODZINY",IF(SUM(S31:U31)>P31,"ESTIMATION: NADGODZINY","-")))) -> - | Y31: =IF(OR(J31="KP",J31="BT",J31="LOBBY",J31="B"),(L31*1.1948)+0.7,"-") -> - | AB31: =IF(L31<VLOOKUP($C$5,DANE!$J$3:$N$14,4,FALSE),VLOOKUP($C$5,DANE!$J$3:$N$14,4,FALSE)*M31,L31*M31) -> 0 | AD31: =AB31*$Y$4 -> 0 | AE31: =AB31*$Y$6 -> 0 | AF31: =M31*$Y$16 -> 0 | AG31: =K31*$Y$13 -> 0 | AJ31: =SUM(AB31:AG31) -> 0 | AM31: =N31*IF(L31<VLOOKUP($C$5,DANE!$J$3:$N$14,4,FALSE),VLOOKUP($C$5,DANE!$J$3:$N$14,4,FALSE),L31)*$AP$22 -> 0 | AN31: =AM31*$Y$4*$AP$22 -> 0 | AO31: =SUM(AM31:AN31) -> 0 | AS31: =O31*IF(L31<VLOOKUP($C$5,DANE!$J$3:$N$14,4,FALSE),VLOOKUP($C$5,DANE!$J$3:$N$14,4,FALSE),L31) -> 0 | AT31: =AS31*$Y$4 -> 0 | AU31: =O31*$Y$16 -> 0 | AV31: =SUM(AS31:AT31) -> 0 | AY31: =IF(L31<VLOOKUP($C$5,DANE!$J$3:$N$14,4,FALSE),VLOOKUP($C$5,DANE!$J$3:$N$14,4,FALSE)*S31,L31*S31) -> 0 | BA31: =AY31*$Y$4 -> 0 | BB31: =AY31*$Y$6 -> 0 | BC31: =S31*$Y$16 -> 0 | BD31: =K31*$Y$13 -> 0 | BG31: =SUM(AY31:BD31) -> 0 | BJ31: =T31*IF(L31<VLOOKUP($C$5,DANE!$J$3:$N$14,4,FALSE),VLOOKUP($C$5,DANE!$J$3:$N$14,4,FALSE),L31)*$BM$22 -> 0 | BK31: =BJ31*$Y$4*$BM$22 -> 0 | BL31: =SUM(BJ31:BK31) -> 0 | BP31: =U31*IF(L31<VLOOKUP($C$5,DANE!$J$3:$N$14,4,FALSE),VLOOKUP($C$5,DANE!$J$3:$N$14,4,FALSE),L31) -> 0 | BQ31: =BP31*$Y$4 -> 0 | BR31: =U31*$Y$16 -> 0 | BS31: =SUM(BP31:BQ31) -> 0
B32: MATRIX PLAN | C32: Plan A | P32: =IFERROR(IF(Q32="tak",$C$8/8*7*K32,K32*$C$8),"") -> 0 | W32: =IF(AND(SUM(M32:O32)<P32,(SUM(M32:O32)>0)),"TARGET: NIEDOGODZINY",IF(SUM(M32:O32)>P32,"TARGET: NADGODZINY",IF(AND(SUM(S32:U32)<P32,(SUM(S32:U32)>0)),"ESTIMATION: NIEDOGODZINY",IF(SUM(S32:U32)>P32,"ESTIMATION: NADGODZINY","-")))) -> - | Y32: =IF(OR(J32="KP",J32="BT",J32="LOBBY",J32="B"),(L32*1.1948)+0.7,"-") -> - | AB32: =IF(L32<VLOOKUP($C$5,DANE!$J$3:$N$14,4,FALSE),VLOOKUP($C$5,DANE!$J$3:$N$14,4,FALSE)*M32,L32*M32) -> 0 | AD32: =AB32*$Y$4 -> 0 | AE32: =AB32*$Y$6 -> 0 | AF32: =M32*$Y$16 -> 0 | AG32: =K32*$Y$13 -> 0 | AJ32: =SUM(AB32:AG32) -> 0 | AM32: =N32*IF(L32<VLOOKUP($C$5,DANE!$J$3:$N$14,4,FALSE),VLOOKUP($C$5,DANE!$J$3:$N$14,4,FALSE),L32)*$AP$22 -> 0 | AN32: =AM32*$Y$4*$AP$22 -> 0 | AO32: =SUM(AM32:AN32) -> 0 | AS32: =O32*IF(L32<VLOOKUP($C$5,DANE!$J$3:$N$14,4,FALSE),VLOOKUP($C$5,DANE!$J$3:$N$14,4,FALSE),L32) -> 0 | AT32: =AS32*$Y$4 -> 0 | AU32: =O32*$Y$16 -> 0 | AV32: =SUM(AS32:AT32) -> 0 | AY32: =IF(L32<VLOOKUP($C$5,DANE!$J$3:$N$14,4,FALSE),VLOOKUP($C$5,DANE!$J$3:$N$14,4,FALSE)*S32,L32*S32) -> 0 | BA32: =AY32*$Y$4 -> 0 | BB32: =AY32*$Y$6 -> 0 | BC32: =S32*$Y$16 -> 0 | BD32: =K32*$Y$13 -> 0 | BG32: =SUM(AY32:BD32) -> 0 | BJ32: =T32*IF(L32<VLOOKUP($C$5,DANE!$J$3:$N$14,4,FALSE),VLOOKUP($C$5,DANE!$J$3:$N$14,4,FALSE),L32)*$BM$22 -> 0 | BK32: =BJ32*$Y$4*$BM$22 -> 0 | BL32: =SUM(BJ32:BK32) -> 0 | BP32: =U32*IF(L32<VLOOKUP($C$5,DANE!$J$3:$N$14,4,FALSE),VLOOKUP($C$5,DANE!$J$3:$N$14,4,FALSE),L32) -> 0 | BQ32: =BP32*$Y$4 -> 0 | BR32: =U32*$Y$16 -> 0 | BS32: =SUM(BP32:BQ32) -> 0
B33: TPLH SUGGESTED | C33: =IFERROR(($C$11/$C$7)/(($C$11/$C$7)/((($C$11/$C$7)/$C$13)*DANE!$R$2+DANE!$S$2)),"") | D33: =IFERROR(HLOOKUP($C$5,'TPLH PLAN'!$B$1:$M$2,2,FALSE),"") -> 0 | E33: =IFERROR(E11/E36,"") -> 5.6609279 | F33: =IFERROR(F11/F36,"") | P33: =IFERROR(IF(Q33="tak",$C$8/8*7*K33,K33*$C$8),"") -> 0 | W33: =IF(AND(SUM(M33:O33)<P33,(SUM(M33:O33)>0)),"TARGET: NIEDOGODZINY",IF(SUM(M33:O33)>P33,"TARGET: NADGODZINY",IF(AND(SUM(S33:U33)<P33,(SUM(S33:U33)>0)),"ESTIMATION: NIEDOGODZINY",IF(SUM(S33:U33)>P33,"ESTIMATION: NADGODZINY","-")))) -> - | Y33: =IF(OR(J33="KP",J33="BT",J33="LOBBY",J33="B"),(L33*1.1948)+0.7,"-") -> - | AB33: =IF(L33<VLOOKUP($C$5,DANE!$J$3:$N$14,4,FALSE),VLOOKUP($C$5,DANE!$J$3:$N$14,4,FALSE)*M33,L33*M33) -> 0 | AD33: =AB33*$Y$4 -> 0 | AE33: =AB33*$Y$6 -> 0 | AF33: =M33*$Y$16 -> 0 | AG33: =K33*$Y$13 -> 0 | AJ33: =SUM(AB33:AG33) -> 0 | AM33: =N33*IF(L33<VLOOKUP($C$5,DANE!$J$3:$N$14,4,FALSE),VLOOKUP($C$5,DANE!$J$3:$N$14,4,FALSE),L33)*$AP$22 -> 0 | AN33: =AM33*$Y$4*$AP$22 -> 0 | AO33: =SUM(AM33:AN33) -> 0 | AS33: =O33*IF(L33<VLOOKUP($C$5,DANE!$J$3:$N$14,4,FALSE),VLOOKUP($C$5,DANE!$J$3:$N$14,4,FALSE),L33) -> 0 | AT33: =AS33*$Y$4 -> 0 | AU33: =O33*$Y$16 -> 0 | AV33: =SUM(AS33:AT33) -> 0 | AY33: =IF(L33<VLOOKUP($C$5,DANE!$J$3:$N$14,4,FALSE),VLOOKUP($C$5,DANE!$J$3:$N$14,4,FALSE)*S33,L33*S33) -> 0 | BA33: =AY33*$Y$4 -> 0 | BB33: =AY33*$Y$6 -> 0 | BC33: =S33*$Y$16 -> 0 | BD33: =K33*$Y$13 -> 0 | BG33: =SUM(AY33:BD33) -> 0 | BJ33: =T33*IF(L33<VLOOKUP($C$5,DANE!$J$3:$N$14,4,FALSE),VLOOKUP($C$5,DANE!$J$3:$N$14,4,FALSE),L33)*$BM$22 -> 0 | BK33: =BJ33*$Y$4*$BM$22 -> 0 | BL33: =SUM(BJ33:BK33) -> 0 | BP33: =U33*IF(L33<VLOOKUP($C$5,DANE!$J$3:$N$14,4,FALSE),VLOOKUP($C$5,DANE!$J$3:$N$14,4,FALSE),L33) -> 0 | BQ33: =BP33*$Y$4 -> 0 | BR33: =U33*$Y$16 -> 0 | BS33: =SUM(BP33:BQ33) -> 0
P34: =IFERROR(IF(Q34="tak",$C$8/8*7*K34,K34*$C$8),"") -> 0 | W34: =IF(AND(SUM(M34:O34)<P34,(SUM(M34:O34)>0)),"TARGET: NIEDOGODZINY",IF(SUM(M34:O34)>P34,"TARGET: NADGODZINY",IF(AND(SUM(S34:U34)<P34,(SUM(S34:U34)>0)),"ESTIMATION: NIEDOGODZINY",IF(SUM(S34:U34)>P34,"ESTIMATION: NADGODZINY","-")))) -> - | Y34: =IF(OR(J34="KP",J34="BT",J34="LOBBY",J34="B"),(L34*1.1948)+0.7,"-") -> - | AB34: =IF(L34<VLOOKUP($C$5,DANE!$J$3:$N$14,4,FALSE),VLOOKUP($C$5,DANE!$J$3:$N$14,4,FALSE)*M34,L34*M34) -> 0 | AD34: =AB34*$Y$4 -> 0 | AE34: =AB34*$Y$6 -> 0 | AF34: =M34*$Y$16 -> 0 | AG34: =K34*$Y$13 -> 0 | AJ34: =SUM(AB34:AG34) -> 0 | AM34: =N34*IF(L34<VLOOKUP($C$5,DANE!$J$3:$N$14,4,FALSE),VLOOKUP($C$5,DANE!$J$3:$N$14,4,FALSE),L34)*$AP$22 -> 0 | AN34: =AM34*$Y$4*$AP$22 -> 0 | AO34: =SUM(AM34:AN34) -> 0 | AS34: =O34*IF(L34<VLOOKUP($C$5,DANE!$J$3:$N$14,4,FALSE),VLOOKUP($C$5,DANE!$J$3:$N$14,4,FALSE),L34) -> 0 | AT34: =AS34*$Y$4 -> 0 | AU34: =O34*$Y$16 -> 0 | AV34: =SUM(AS34:AT34) -> 0 | AY34: =IF(L34<VLOOKUP($C$5,DANE!$J$3:$N$14,4,FALSE),VLOOKUP($C$5,DANE!$J$3:$N$14,4,FALSE)*S34,L34*S34) -> 0 | BA34: =AY34*$Y$4 -> 0 | BB34: =AY34*$Y$6 -> 0 | BC34: =S34*$Y$16 -> 0 | BD34: =K34*$Y$13 -> 0 | BG34: =SUM(AY34:BD34) -> 0 | BJ34: =T34*IF(L34<VLOOKUP($C$5,DANE!$J$3:$N$14,4,FALSE),VLOOKUP($C$5,DANE!$J$3:$N$14,4,FALSE),L34)*$BM$22 -> 0 | BK34: =BJ34*$Y$4*$BM$22 -> 0 | BL34: =SUM(BJ34:BK34) -> 0 | BP34: =U34*IF(L34<VLOOKUP($C$5,DANE!$J$3:$N$14,4,FALSE),VLOOKUP($C$5,DANE!$J$3:$N$14,4,FALSE),L34) -> 0 | BQ34: =BP34*$Y$4 -> 0 | BR34: =U34*$Y$16 -> 0 | BS34: =SUM(BP34:BQ34) -> 0
B35: TPLH TARGET | C35: 6.6 | P35: =IFERROR(IF(Q35="tak",$C$8/8*7*K35,K35*$C$8),"") -> 0 | W35: =IF(AND(SUM(M35:O35)<P35,(SUM(M35:O35)>0)),"TARGET: NIEDOGODZINY",IF(SUM(M35:O35)>P35,"TARGET: NADGODZINY",IF(AND(SUM(S35:U35)<P35,(SUM(S35:U35)>0)),"ESTIMATION: NIEDOGODZINY",IF(SUM(S35:U35)>P35,"ESTIMATION: NADGODZINY","-")))) -> - | Y35: =IF(OR(J35="KP",J35="BT",J35="LOBBY",J35="B"),(L35*1.1948)+0.7,"-") -> - | AB35: =IF(L35<VLOOKUP($C$5,DANE!$J$3:$N$14,4,FALSE),VLOOKUP($C$5,DANE!$J$3:$N$14,4,FALSE)*M35,L35*M35) -> 0 | AD35: =AB35*$Y$4 -> 0 | AE35: =AB35*$Y$6 -> 0 | AF35: =M35*$Y$16 -> 0 | AG35: =K35*$Y$13 -> 0 | AJ35: =SUM(AB35:AG35) -> 0 | AM35: =N35*IF(L35<VLOOKUP($C$5,DANE!$J$3:$N$14,4,FALSE),VLOOKUP($C$5,DANE!$J$3:$N$14,4,FALSE),L35)*$AP$22 -> 0 | AN35: =AM35*$Y$4*$AP$22 -> 0 | AO35: =SUM(AM35:AN35) -> 0 | AS35: =O35*IF(L35<VLOOKUP($C$5,DANE!$J$3:$N$14,4,FALSE),VLOOKUP($C$5,DANE!$J$3:$N$14,4,FALSE),L35) -> 0 | AT35: =AS35*$Y$4 -> 0 | AU35: =O35*$Y$16 -> 0 | AV35: =SUM(AS35:AT35) -> 0 | AY35: =IF(L35<VLOOKUP($C$5,DANE!$J$3:$N$14,4,FALSE),VLOOKUP($C$5,DANE!$J$3:$N$14,4,FALSE)*S35,L35*S35) -> 0 | BA35: =AY35*$Y$4 -> 0 | BB35: =AY35*$Y$6 -> 0 | BC35: =S35*$Y$16 -> 0 | BD35: =K35*$Y$13 -> 0 | BG35: =SUM(AY35:BD35) -> 0 | BJ35: =T35*IF(L35<VLOOKUP($C$5,DANE!$J$3:$N$14,4,FALSE),VLOOKUP($C$5,DANE!$J$3:$N$14,4,FALSE),L35)*$BM$22 -> 0 | BK35: =BJ35*$Y$4*$BM$22 -> 0 | BL35: =SUM(BJ35:BK35) -> 0 | BP35: =U35*IF(L35<VLOOKUP($C$5,DANE!$J$3:$N$14,4,FALSE),VLOOKUP($C$5,DANE!$J$3:$N$14,4,FALSE),L35) -> 0 | BQ35: =BP35*$Y$4 -> 0 | BR35: =U35*$Y$16 -> 0 | BS35: =SUM(BP35:BQ35) -> 0
B36: TOTAL WORKING HOURS | C36: =IFERROR(M18+M41+M66,"") -> 1760 | E36: =IFERROR(S18+S41+S66,"") -> 1713.5 | P36: =IFERROR(IF(Q36="tak",$C$8/8*7*K36,K36*$C$8),"") -> 0 | W36: =IF(AND(SUM(M36:O36)<P36,(SUM(M36:O36)>0)),"TARGET: NIEDOGODZINY",IF(SUM(M36:O36)>P36,"TARGET: NADGODZINY",IF(AND(SUM(S36:U36)<P36,(SUM(S36:U36)>0)),"ESTIMATION: NIEDOGODZINY",IF(SUM(S36:U36)>P36,"ESTIMATION: NADGODZINY","-")))) -> - | Y36: =IF(OR(J36="KP",J36="BT",J36="LOBBY",J36="B"),(L36*1.1948)+0.7,"-") -> - | AB36: =IF(L36<VLOOKUP($C$5,DANE!$J$3:$N$14,4,FALSE),VLOOKUP($C$5,DANE!$J$3:$N$14,4,FALSE)*M36,L36*M36) -> 0 | AD36: =AB36*$Y$4 -> 0 | AE36: =AB36*$Y$6 -> 0 | AF36: =M36*$Y$16 -> 0 | AG36: =K36*$Y$13 -> 0 | AJ36: =SUM(AB36:AG36) -> 0 | AM36: =N36*IF(L36<VLOOKUP($C$5,DANE!$J$3:$N$14,4,FALSE),VLOOKUP($C$5,DANE!$J$3:$N$14,4,FALSE),L36)*$AP$22 -> 0 | AN36: =AM36*$Y$4*$AP$22 -> 0 | AO36: =SUM(AM36:AN36) -> 0 | AS36: =O36*IF(L36<VLOOKUP($C$5,DANE!$J$3:$N$14,4,FALSE),VLOOKUP($C$5,DANE!$J$3:$N$14,4,FALSE),L36) -> 0 | AT36: =AS36*$Y$4 -> 0 | AU36: =O36*$Y$16 -> 0 | AV36: =SUM(AS36:AT36) -> 0 | AY36: =IF(L36<VLOOKUP($C$5,DANE!$J$3:$N$14,4,FALSE),VLOOKUP($C$5,DANE!$J$3:$N$14,4,FALSE)*S36,L36*S36) -> 0 | BA36: =AY36*$Y$4 -> 0 | BB36: =AY36*$Y$6 -> 0 | BC36: =S36*$Y$16 -> 0 | BD36: =K36*$Y$13 -> 0 | BG36: =SUM(AY36:BD36) -> 0 | BJ36: =T36*IF(L36<VLOOKUP($C$5,DANE!$J$3:$N$14,4,FALSE),VLOOKUP($C$5,DANE!$J$3:$N$14,4,FALSE),L36)*$BM$22 -> 0 | BK36: =BJ36*$Y$4*$BM$22 -> 0 | BL36: =SUM(BJ36:BK36) -> 0 | BP36: =U36*IF(L36<VLOOKUP($C$5,DANE!$J$3:$N$14,4,FALSE),VLOOKUP($C$5,DANE!$J$3:$N$14,4,FALSE),L36) -> 0 | BQ36: =BP36*$Y$4 -> 0 | BR36: =U36*$Y$16 -> 0 | BS36: =SUM(BP36:BQ36) -> 0
P37: =IFERROR(IF(Q37="tak",$C$8/8*7*K37,K37*$C$8),"") -> 0 | W37: =IF(AND(SUM(M37:O37)<P37,(SUM(M37:O37)>0)),"TARGET: NIEDOGODZINY",IF(SUM(M37:O37)>P37,"TARGET: NADGODZINY",IF(AND(SUM(S37:U37)<P37,(SUM(S37:U37)>0)),"ESTIMATION: NIEDOGODZINY",IF(SUM(S37:U37)>P37,"ESTIMATION: NADGODZINY","-")))) -> - | Y37: =IF(OR(J37="KP",J37="BT",J37="LOBBY",J37="B"),(L37*1.1948)+0.7,"-") -> - | AB37: =IF(L37<VLOOKUP($C$5,DANE!$J$3:$N$14,4,FALSE),VLOOKUP($C$5,DANE!$J$3:$N$14,4,FALSE)*M37,L37*M37) -> 0 | AD37: =AB37*$Y$4 -> 0 | AE37: =AB37*$Y$6 -> 0 | AF37: =M37*$Y$16 -> 0 | AG37: =K37*$Y$13 -> 0 | AJ37: =SUM(AB37:AG37) -> 0 | AM37: =N37*IF(L37<VLOOKUP($C$5,DANE!$J$3:$N$14,4,FALSE),VLOOKUP($C$5,DANE!$J$3:$N$14,4,FALSE),L37)*$AP$22 -> 0 | AN37: =AM37*$Y$4*$AP$22 -> 0 | AO37: =SUM(AM37:AN37) -> 0 | AS37: =O37*IF(L37<VLOOKUP($C$5,DANE!$J$3:$N$14,4,FALSE),VLOOKUP($C$5,DANE!$J$3:$N$14,4,FALSE),L37) -> 0 | AT37: =AS37*$Y$4 -> 0 | AU37: =O37*$Y$16 -> 0 | AV37: =SUM(AS37:AT37) -> 0 | AY37: =IF(L37<VLOOKUP($C$5,DANE!$J$3:$N$14,4,FALSE),VLOOKUP($C$5,DANE!$J$3:$N$14,4,FALSE)*S37,L37*S37) -> 0 | BA37: =AY37*$Y$4 -> 0 | BB37: =AY37*$Y$6 -> 0 | BC37: =S37*$Y$16 -> 0 | BD37: =K37*$Y$13 -> 0 | BG37: =SUM(AY37:BD37) -> 0 | BJ37: =T37*IF(L37<VLOOKUP($C$5,DANE!$J$3:$N$14,4,FALSE),VLOOKUP($C$5,DANE!$J$3:$N$14,4,FALSE),L37)*$BM$22 -> 0 | BK37: =BJ37*$Y$4*$BM$22 -> 0 | BL37: =SUM(BJ37:BK37) -> 0 | BP37: =U37*IF(L37<VLOOKUP($C$5,DANE!$J$3:$N$14,4,FALSE),VLOOKUP($C$5,DANE!$J$3:$N$14,4,FALSE),L37) -> 0 | BQ37: =BP37*$Y$4 -> 0 | BR37: =U37*$Y$16 -> 0 | BS37: =SUM(BP37:BQ37) -> 0
B38: WORKING HOURS BUDGET | C38: =IFERROR(C11/C35,"WPROWADŹ TPLH TARGET") -> 1651.5152 | D38: =IFERROR(D11/D33,"-") -> - | P38: =IFERROR(IF(Q38="tak",$C$8/8*7*K38,K38*$C$8),"") -> 0 | W38: =IF(AND(SUM(M38:O38)<P38,(SUM(M38:O38)>0)),"TARGET: NIEDOGODZINY",IF(SUM(M38:O38)>P38,"TARGET: NADGODZINY",IF(AND(SUM(S38:U38)<P38,(SUM(S38:U38)>0)),"ESTIMATION: NIEDOGODZINY",IF(SUM(S38:U38)>P38,"ESTIMATION: NADGODZINY","-")))) -> - | Y38: =IF(OR(J38="KP",J38="BT",J38="LOBBY",J38="B"),(L38*1.1948)+0.7,"-") -> - | AB38: =IF(L38<VLOOKUP($C$5,DANE!$J$3:$N$14,4,FALSE),VLOOKUP($C$5,DANE!$J$3:$N$14,4,FALSE)*M38,L38*M38) -> 0 | AD38: =AB38*$Y$4 -> 0 | AE38: =AB38*$Y$6 -> 0 | AF38: =M38*$Y$16 -> 0 | AG38: =K38*$Y$13 -> 0 | AJ38: =SUM(AB38:AG38) -> 0 | AM38: =N38*IF(L38<VLOOKUP($C$5,DANE!$J$3:$N$14,4,FALSE),VLOOKUP($C$5,DANE!$J$3:$N$14,4,FALSE),L38)*$AP$22 -> 0 | AN38: =AM38*$Y$4*$AP$22 -> 0 | AO38: =SUM(AM38:AN38) -> 0 | AS38: =O38*IF(L38<VLOOKUP($C$5,DANE!$J$3:$N$14,4,FALSE),VLOOKUP($C$5,DANE!$J$3:$N$14,4,FALSE),L38) -> 0 | AT38: =AS38*$Y$4 -> 0 | AU38: =O38*$Y$16 -> 0 | AV38: =SUM(AS38:AT38) -> 0 | AY38: =IF(L38<VLOOKUP($C$5,DANE!$J$3:$N$14,4,FALSE),VLOOKUP($C$5,DANE!$J$3:$N$14,4,FALSE)*S38,L38*S38) -> 0 | BA38: =AY38*$Y$4 -> 0 | BB38: =AY38*$Y$6 -> 0 | BC38: =S38*$Y$16 -> 0 | BD38: =K38*$Y$13 -> 0 | BG38: =SUM(AY38:BD38) -> 0 | BJ38: =T38*IF(L38<VLOOKUP($C$5,DANE!$J$3:$N$14,4,FALSE),VLOOKUP($C$5,DANE!$J$3:$N$14,4,FALSE),L38)*$BM$22 -> 0 | BK38: =BJ38*$Y$4*$BM$22 -> 0 | BL38: =SUM(BJ38:BK38) -> 0 | BP38: =U38*IF(L38<VLOOKUP($C$5,DANE!$J$3:$N$14,4,FALSE),VLOOKUP($C$5,DANE!$J$3:$N$14,4,FALSE),L38) -> 0 | BQ38: =BP38*$Y$4 -> 0 | BR38: =U38*$Y$16 -> 0 | BS38: =SUM(BP38:BQ38) -> 0
P39: =IFERROR(IF(Q39="tak",$C$8/8*7*K39,K39*$C$8),"") -> 0 | W39: =IF(AND(SUM(M39:O39)<P39,(SUM(M39:O39)>0)),"TARGET: NIEDOGODZINY",IF(SUM(M39:O39)>P39,"TARGET: NADGODZINY",IF(AND(SUM(S39:U39)<P39,(SUM(S39:U39)>0)),"ESTIMATION: NIEDOGODZINY",IF(SUM(S39:U39)>P39,"ESTIMATION: NADGODZINY","-")))) -> - | Y39: =IF(OR(J39="KP",J39="BT",J39="LOBBY",J39="B"),(L39*1.1948)+0.7,"-") -> - | AB39: =IF(L39<VLOOKUP($C$5,DANE!$J$3:$N$14,4,FALSE),VLOOKUP($C$5,DANE!$J$3:$N$14,4,FALSE)*M39,L39*M39) -> 0 | AD39: =AB39*$Y$4 -> 0 | AE39: =AB39*$Y$6 -> 0 | AF39: =M39*$Y$16 -> 0 | AG39: =K39*$Y$13 -> 0 | AJ39: =SUM(AB39:AG39) -> 0 | AM39: =N39*IF(L39<VLOOKUP($C$5,DANE!$J$3:$N$14,4,FALSE),VLOOKUP($C$5,DANE!$J$3:$N$14,4,FALSE),L39)*$AP$22 -> 0 | AN39: =AM39*$Y$4*$AP$22 -> 0 | AO39: =SUM(AM39:AN39) -> 0 | AS39: =O39*IF(L39<VLOOKUP($C$5,DANE!$J$3:$N$14,4,FALSE),VLOOKUP($C$5,DANE!$J$3:$N$14,4,FALSE),L39) -> 0 | AT39: =AS39*$Y$4 -> 0 | AU39: =O39*$Y$16 -> 0 | AV39: =SUM(AS39:AT39) -> 0 | AY39: =IF(L39<VLOOKUP($C$5,DANE!$J$3:$N$14,4,FALSE),VLOOKUP($C$5,DANE!$J$3:$N$14,4,FALSE)*S39,L39*S39) -> 0 | BA39: =AY39*$Y$4 -> 0 | BB39: =AY39*$Y$6 -> 0 | BC39: =S39*$Y$16 -> 0 | BD39: =K39*$Y$13 -> 0 | BG39: =SUM(AY39:BD39) -> 0 | BJ39: =T39*IF(L39<VLOOKUP($C$5,DANE!$J$3:$N$14,4,FALSE),VLOOKUP($C$5,DANE!$J$3:$N$14,4,FALSE),L39)*$BM$22 -> 0 | BK39: =BJ39*$Y$4*$BM$22 -> 0 | BL39: =SUM(BJ39:BK39) -> 0 | BP39: =U39*IF(L39<VLOOKUP($C$5,DANE!$J$3:$N$14,4,FALSE),VLOOKUP($C$5,DANE!$J$3:$N$14,4,FALSE),L39) -> 0 | BQ39: =BP39*$Y$4 -> 0 | BR39: =U39*$Y$16 -> 0 | BS39: =SUM(BP39:BQ39) -> 0
P40: =IFERROR(IF(Q40="tak",$C$8/8*7*K40,K40*$C$8),"") -> 0 | W40: =IF(AND(SUM(M40:O40)<P40,(SUM(M40:O40)>0)),"TARGET: NIEDOGODZINY",IF(SUM(M40:O40)>P40,"TARGET: NADGODZINY",IF(AND(SUM(S40:U40)<P40,(SUM(S40:U40)>0)),"ESTIMATION: NIEDOGODZINY",IF(SUM(S40:U40)>P40,"ESTIMATION: NADGODZINY","-")))) -> - | Y40: =IF(OR(J40="KP",J40="BT",J40="LOBBY",J40="B"),(L40*1.1948)+0.7,"-") -> - | AB40: =IF(L40<VLOOKUP($C$5,DANE!$J$3:$N$14,4,FALSE),VLOOKUP($C$5,DANE!$J$3:$N$14,4,FALSE)*M40,L40*M40) -> 0 | AD40: =AB40*$Y$4 -> 0 | AE40: =AB40*$Y$6 -> 0 | AF40: =M40*$Y$16 -> 0 | AG40: =K40*$Y$13 -> 0 | AJ40: =SUM(AB40:AG40) -> 0 | AM40: =N40*IF(L40<VLOOKUP($C$5,DANE!$J$3:$N$14,4,FALSE),VLOOKUP($C$5,DANE!$J$3:$N$14,4,FALSE),L40)*$AP$22 -> 0 | AN40: =AM40*$Y$4*$AP$22 -> 0 | AO40: =SUM(AM40:AN40) -> 0 | AS40: =O40*IF(L40<VLOOKUP($C$5,DANE!$J$3:$N$14,4,FALSE),VLOOKUP($C$5,DANE!$J$3:$N$14,4,FALSE),L40) -> 0 | AT40: =AS40*$Y$4 -> 0 | AU40: =O40*$Y$16 -> 0 | AV40: =SUM(AS40:AT40) -> 0 | AY40: =IF(L40<VLOOKUP($C$5,DANE!$J$3:$N$14,4,FALSE),VLOOKUP($C$5,DANE!$J$3:$N$14,4,FALSE)*S40,L40*S40) -> 0 | BA40: =AY40*$Y$4 -> 0 | BB40: =AY40*$Y$6 -> 0 | BC40: =S40*$Y$16 -> 0 | BD40: =K40*$Y$13 -> 0 | BG40: =SUM(AY40:BD40) -> 0 | BJ40: =T40*IF(L40<VLOOKUP($C$5,DANE!$J$3:$N$14,4,FALSE),VLOOKUP($C$5,DANE!$J$3:$N$14,4,FALSE),L40)*$BM$22 -> 0 | BK40: =BJ40*$Y$4*$BM$22 -> 0 | BL40: =SUM(BJ40:BK40) -> 0 | BP40: =U40*IF(L40<VLOOKUP($C$5,DANE!$J$3:$N$14,4,FALSE),VLOOKUP($C$5,DANE!$J$3:$N$14,4,FALSE),L40) -> 0 | BQ40: =BP40*$Y$4 -> 0 | BR40: =U40*$Y$16 -> 0 | BS40: =SUM(BP40:BQ40) -> 0
B41: Check what would be the TPLH improvement impact on your store COL | C41: TPLH improvement | D41: COL savings | E41: COL % influence | H41: UMOWA O PRACĘ TOTAL: | K41: =SUM(K22:K40) -> 1.25 | M41: =SUM(M22:M40) -> 220 | N41: =SUM(N22:N40) -> 0 | O41: =SUM(O22:O40) -> 0 | P41: =SUM(P22:P40) -> 220 | S41: =SUM(S22:S40) -> 205 | T41: =SUM(T22:T40) -> 0 | U41: =SUM(U22:U40) -> 0 | V41: =SUM(V22:V40) -> 0 | AB41: =SUM(AB22:AB40) -> 6822.2 | AD41: =SUM(AD22:AD40) -> 1154.9985 | AE41: =SUM(AE22:AE40) -> 173.9661 | AF41: =SUM(AF22:AF40) -> 187 | AG41: =SUM(AG22:AG40) -> 250 | AJ41: =SUM(AJ22:AJ40) -> 8588.1646 | AM41: =SUM(AM22:AM40) -> 0 | AN41: =SUM(AN22:AN40) -> 0 | AO41: =SUM(AO22:AO40) -> 0 | AS41: =SUM(AS22:AS40) -> 0 | AT41: =SUM(AT22:AT40) -> 0 | AU41: =SUM(AU22:AU40) -> 0 | AV41: =SUM(AV22:AV40) -> 0 | AY41: =SUM(AY22:AY40) -> 6359 | BA41: =SUM(BA22:BA40) -> 1076.5787 | BB41: =SUM(BB22:BB40) -> 162.1545 | BC41: =SUM(BC22:BC40) -> 174.25 | BD41: =SUM(BD22:BD40) -> 250 | BG41: =SUM(BG22:BG40) -> 8021.9832 | BJ41: =SUM(BJ22:BJ40) -> 0 | BK41: =SUM(BK22:BK40) -> 0 | BL41: =SUM(BL22:BL40) -> 0 | BP41: =SUM(BP22:BP40) -> 0 | BQ41: =SUM(BQ22:BQ40) -> 0 | BR41: =SUM(BR22:BR40) -> 0 | BS41: =SUM(BS22:BS40) -> 0
C42: 7.0 | D42: =IFERROR((C11/(C23)-C11/(C23+C42))*(AJ41+AJ66)/C22,"") | E42: =IFERROR(-D42/C9,"") | H42: UMOWA ZLECENIE - TARGET | I42: Imię i Nazwisko | J42: Stanowisko | L42: Stawka brutto | M42: Planowany czas pracy | Q42: UMOWA ZLECENIE- ESTIMATION | S42: Rzeczywisty czas pracy | V42: Bonus | X42: Hourly Job - Barista | AA42: UMOWA ZLECENIE- TARGET | AJ42: COL TOTAL | AX42: UMOWA ZLECENIE- ESTIMATION | BG42: COL TOTAL
B44: COL | C44: PLAN | D44: AOP | E44: ESTIMATION | F44: P&L | I44: Wiktoria Lenart | J44: BT | L44: 31.4 | M44: 30 | S44: 45 | V44: 50 | X44: =IF(OR(J44="KP",J44="BT",J44="LOBBY",J44="B"),L44,"-") -> 31.4 | AJ44: =L44*M44 -> 942 | BG44: =S44*L44 -> 1413
C45: =IFERROR(SUM(C46,C53,C65),"") -> 78032.621 | D45: =IFERROR(VLOOKUP("COL",AOP!$A$2:$Z$100,VLOOKUP($C$5,DANE!$B$17:$C$28,2,FALSE),FALSE),0) -> 0 | E45: =IFERROR(SUM(E46,E53,E65),"") -> 76149.551 | F45: =SUM(F46,F53,F65) -> 0 | I45: Wiktoria Walczak | J45: BT | L45: 31.4 | M45: 30 | S45: 47.5 | X45: =IF(OR(J45="KP",J45="BT",J45="LOBBY",J45="B"),L45,"-") -> 31.4 | AJ45: =L45*M45 -> 942 | BG45: =S45*L45 -> 1491.5
B46: MANAGER | C46: =IFERROR(SUM(C47:C52),"") -> 39754.393 | D46: =IFERROR(SUM(D47:D52),"") -> 0 | E46: =IFERROR(SUM(E47:E52),"") -> 38446.558 | F46: =SUM(F47:F52) -> 0 | I46: Marysia Szulczyk | J46: BT | L46: 31.4 | M46: 50 | S46: 30.5 | X46: =IF(OR(J46="KP",J46="BT",J46="LOBBY",J46="B"),L46,"-") -> 31.4 | AJ46: =L46*M46 -> 1570 | BG46: =S46*L46 -> 957.7
B47: Payroll Manager | C47: =IFERROR(AB18+AF18,"") -> 30699 | D47: =IFERROR(VLOOKUP(B47,AOP!$A$2:$Z$100,VLOOKUP($C$5,DANE!$B$17:$C$28,2,FALSE),FALSE),0) -> 0 | E47: =IFERROR(AY18+BC18,"") -> 29038.545 | I47: Zuzanna Dworak | J47: B | L47: 30.4 | M47: 30 | S47: 39.5 | X47: =IF(OR(J47="KP",J47="BT",J47="LOBBY",J47="B"),L47,"-") -> 30.4 | AJ47: =L47*M47 -> 912 | BG47: =S47*L47 -> 1200.8
B48: Bonus Manager | C48: =IFERROR(AC18+AI18+AC19,"") -> 1052 | D48: =IFERROR(VLOOKUP(B48,AOP!$A$2:$Z$100,VLOOKUP($C$5,DANE!$B$17:$C$28,2,FALSE),FALSE),0) -> 0 | E48: =IFERROR(AZ18+BF18+AZ19,"") -> 1352 | I48: Aleksandra Płużycka | J48: B | L48: 30.5 | M48: 30 | S48: 56 | X48: =IF(OR(J48="KP",J48="BT",J48="LOBBY",J48="B"),L48,"-") -> 30.5 | AJ48: =L48*M48 -> 915 | BG48: =S48*L48 -> 1708
B49: Social Contribution Manager | C49: =IFERROR(AD18+M75,"") -> 5004.7059 | D49: =IFERROR(VLOOKUP(B49,AOP!$A$2:$Z$100,VLOOKUP($C$5,DANE!$B$17:$C$28,2,FALSE),FALSE),0) -> 0 | E49: =IFERROR(BA18+S75,"") -> 5050.3245 | I49: Maja Piasecka | J49: B | L49: 30.5 | M49: 30 | S49: 67 | X49: =IF(OR(J49="KP",J49="BT",J49="LOBBY",J49="B"),L49,"-") -> 30.5 | AJ49: =L49*M49 -> 915 | BG49: =S49*L49 -> 2043.5
B50: Disability Fund Manager | C50: =IFERROR(AG18+P71,"") -> 950 | E50: =IFERROR(S71+BD18,"") -> 950 | I50: Julia Zimnicka | J50: B | L50: 30.5 | M50: 50 | S50: 51 | V50: 150 | X50: =IF(OR(J50="KP",J50="BT",J50="LOBBY",J50="B"),L50,"-") -> 30.5 | AJ50: =L50*M50 -> 1525 | BG50: =S50*L50 -> 1555.5
B51: Social Fund Manager | C51: =IFERROR(AE18,"") -> 698.68725 | E51: =IFERROR(BB18,"") -> 705.68816 | I51: Julia Gnieciak | J51: B | L51: 30.5 | M51: 30 | S51: 0 | X51: =IF(OR(J51="KP",J51="BT",J51="LOBBY",J51="B"),L51,"-") -> 30.5 | AJ51: =L51*M51 -> 915 | BG51: =S51*L51 -> 0
B52: Other Manager | C52: =IFERROR(AH18,"") -> 1350 | E52: =BE18 -> 1350 | I52: Magdalena Wiśniewska | J52: B | L52: 30.5 | M52: 50 | S52: 46 | X52: =IF(OR(J52="KP",J52="BT",J52="LOBBY",J52="B"),L52,"-") -> 30.5 | AJ52: =L52*M52 -> 1525 | BG52: =S52*L52 -> 1403
B53: CREW | C53: =IFERROR(SUM(C54:C64)-C54,"") -> 35198.228 | D53: =IFERROR(SUM(D54:D64),"") -> 0 | E53: =IFERROR(SUM(E54:E64)-E54,"") -> 34818.993 | F53: =SUM(F54:F64) -> 0 | I53: Zuzanna Gzula | J53: B | L53: 30.5 | M53: 50 | S53: 45 | X53: =IF(OR(J53="KP",J53="BT",J53="LOBBY",J53="B"),L53,"-") -> 30.5 | AJ53: =L53*M53 -> 1525 | BG53: =S53*L53 -> 1372.5
B54: Payroll Crew | C54: =IFERROR(SUM(C55:C59),"") -> 32115.2 | D54: =IFERROR(VLOOKUP(B54,AOP!$A$2:$Z$100,VLOOKUP($C$5,DANE!$B$17:$C$28,2,FALSE),FALSE),0) -> 0 | E54: =IFERROR(SUM(E55:E59),"") -> 32061.75 | I54: Gabriela Suwald | J54: B | L54: 30.5 | M54: 50 | S54: 44 | X54: =IF(OR(J54="KP",J54="BT",J54="LOBBY",J54="B"),L54,"-") -> 30.5 | AJ54: =L54*M54 -> 1525 | BG54: =S54*L54 -> 1342
B55: Basic Salary Crew | C55: =IFERROR(AB41,"") -> 6822.2 | E55: =IFERROR(AY41,"") -> 6359 | I55: Agnieszka Charmuszko | J55: B | L55: 30.5 | M55: 50 | S55: 33 | X55: =IF(OR(J55="KP",J55="BT",J55="LOBBY",J55="B"),L55,"-") -> 30.5 | AJ55: =L55*M55 -> 1525 | BG55: =S55*L55 -> 1006.5
B56: Sick leave salary-crew | C56: =IFERROR(AM41,"") -> 0 | E56: =IFERROR(BJ41,"") -> 0 | I56: Julia Szulc | J56: B | L56: 30.5 | M56: 30 | S56: 109 | V56: 200 | X56: =IF(OR(J56="KP",J56="BT",J56="LOBBY",J56="B"),L56,"-") -> 30.5 | AJ56: =L56*M56 -> 915 | BG56: =S56*L56 -> 3324.5
B57: Holiday pay-crew | C57: =IFERROR(AS41,"") -> 0 | E57: =IFERROR(BP41,"") -> 0 | I57: Katarzyna Magryta | J57: B | L57: 30.5 | M57: 30 | S57: 0 | X57: =IF(OR(J57="KP",J57="BT",J57="LOBBY",J57="B"),L57,"-") -> 30.5 | AJ57: =L57*M57 -> 915 | BG57: =S57*L57 -> 0
B58: Working clothes equivalent-crew | C58: =IFERROR(AF41+AU41,"") -> 187 | E58: =IFERROR(BC41+BR41,"") -> 174.25 | I58: Emilia Ebert | J58: B | L58: 30.5 | M58: 30 | S58: 87.5 | X58: =IF(OR(J58="KP",J58="BT",J58="LOBBY",J58="B"),L58,"-") -> 30.5 | AJ58: =L58*M58 -> 915 | BG58: =S58*L58 -> 2668.75
B59: Civil contracts salaries-crew | C59: =IFERROR(AJ66,"") -> 25106 | E59: =IFERROR(BG66,"") -> 25528.5 | I59: Uczeń | J59: B | L59: 30.5 | M59: 30 | S59: 0 | X59: =IF(OR(J59="KP",J59="BT",J59="LOBBY",J59="B"),L59,"-") -> 30.5 | AJ59: =L59*M59 -> 915 | BG59: =S59*L59 -> 0
B60: Bonus Crew | C60: =IFERROR(P68+P70,"") -> 600 | D60: =IFERROR(VLOOKUP(B60,AOP!$A$2:$Z$100,VLOOKUP($C$5,DANE!$B$17:$C$28,2,FALSE),FALSE),0) -> 0 | E60: =IFERROR(S68+S70,"") -> 400 | I60: Aleksandra Kurowska | J60: B | L60: 30.5 | M60: 50 | S60: 30.5 | X60: =IF(OR(J60="KP",J60="BT",J60="LOBBY",J60="B"),L60,"-") -> 30.5 | AJ60: =L60*M60 -> 1525 | BG60: =S60*L60 -> 930.25
B61: Social Contribution Crew | C61: =IFERROR(AD41+AD67+AD68+AD69+AD70+AD74+AN41+AT41+P75,"") -> 1309.0615 | D61: =IFERROR(VLOOKUP(B61,AOP!$A$2:$Z$100,VLOOKUP($C$5,DANE!$B$17:$C$28,2,FALSE),FALSE),0) -> 0 | E61: =IFERROR(BA41+BA67+BA68+BA69+BA70+BA74+BK41+BQ41+T75,"") -> 1195.0887 | I61: Małgorzata Kręt | J61: B | L61: 30.5 | M61: 30 | S61: 43 | X61: =IF(OR(J61="KP",J61="BT",J61="LOBBY",J61="B"),L61,"-") -> 30.5 | AJ61: =L61*M61 -> 915 | BG61: =S61*L61 -> 1311.5
B62: Disability Fund Crew | C62: =IFERROR(AG41+P72,"") -> 250 | D62: =IFERROR(VLOOKUP("Disability Fund",AOP!$A$2:$Z$100,VLOOKUP($C$5,DANE!$B$17:$C$28,2,FALSE),FALSE),0) -> 0 | E62: =IFERROR(BD41+S72,"") -> 250 | I62: Anna Rutkowska | J62: B | L62: 30.5 | M62: 70 | S62: 59 | X62: =IF(OR(J62="KP",J62="BT",J62="LOBBY",J62="B"),L62,"-") -> 30.5 | AJ62: =L62*M62 -> 2135 | BG62: =S62*L62 -> 1799.5
B63: Social Fund Crew | C63: =IFERROR(AE41,"") -> 173.9661 | D63: =IFERROR(VLOOKUP("Social Fund",AOP!$A$2:$Z$100,VLOOKUP($C$5,DANE!$B$17:$C$28,2,FALSE),FALSE),0) -> 0 | E63: =IFERROR(BB41,"") -> 162.1545 | I63: Agata Boruc | J63: B | L63: 30.5 | M63: 70 | S63: 0 | X63: =IF(OR(J63="KP",J63="BT",J63="LOBBY",J63="B"),L63,"-") -> 30.5 | AJ63: =L63*M63 -> 2135 | BG63: =S63*L63 -> 0
B64: Other Crew | C64: =IFERROR(P73+P74+P67,"") -> 750 | D64: =IFERROR(VLOOKUP("Other",AOP!$A$2:$Z$100,VLOOKUP($C$5,DANE!$B$17:$C$28,2,FALSE),FALSE),0) -> 0 | E64: =IFERROR(S73+S74+S67,"") -> 750 | X64: =IF(OR(J64="KP",J64="BT",J64="LOBBY",J64="B"),L64,"-") -> - | AJ64: =L64*M64 -> 0 | BG64: =S64*L64 -> 0
B65: DRIVERS | C65: =IFERROR(SUM(C66),"") -> 3080 | D65: =IFERROR(SUM(D66),"") -> 0 | E65: =IFERROR(SUM(E66),"") -> 2884 | F65: =SUM(F66) -> 0 | X65: =IF(OR(J65="KP",J65="BT",J65="LOBBY",J65="B"),L65,"-") -> - | AJ65: =L65*M65 -> 0 | BG65: =S65*L65 -> 0
B66: Drivers | C66: =IFERROR(M76*P76,"") -> 3080 | D66: =IFERROR(VLOOKUP(B66,AOP!$A$2:$Z$100,VLOOKUP($C$5,DANE!$B$17:$C$28,2,FALSE),FALSE),0) -> 0 | E66: =IFERROR(S76*T76,"") -> 2884 | H66: HUMAN RENT TOTAL: | K66: =SUM(M44:M65)/C8 -> 4.6590909 | M66: =SUM(M44:M65) -> 820 | S66: =SUM(S44:S65) -> 833.5 | T66: =SUM(T44:T65) -> 0 | V66: =SUM(V44:W65) -> 400 | AJ66: =SUM(AJ44:AJ65) -> 25106 | BG66: =SUM(BG44:BG65) -> 25528.5
H67: OTHER - TARGET | I67: Medical examination ryczałt | P67: 150 | Q67: OTHER - ESTIMATION | S67: 150 | AA67: OTHER - ESTIMATION | AJ67: =P67+AD67 -> 150 | AX67: OTHER - ESTIMATION | BG67: =S67+BA67 -> 150
C68: TARGET | E68: ESTIMATION | I68: Bonus "Recommend a friend" (netto) | P68: 0 | AD68: =P68*$Y$4 -> 0 | AJ68: =P68+AD68 -> 0 | BA68: =S68*$Y$4 -> 0 | BG68: =S68+BA68 -> 0
B69: PARTNERS TOTAL | C69: =COUNTA(J3:J14,J22:J40,J44:J65) -> 28 | D69: =IFERROR(C69/C$69,"-") -> 1 | E69: =C69 -> 28 | F69: =D69 -> 1 | I69: Bonus SSV No Area | J69: 0.001 | K69: Suggested SSV Bonus | M69: =C9*J69 -> 310 | P69: 300 | S69: =AZ19 -> 300 | AD69: =M69*$Y$4 -> 52.483 | AJ69: =P69+AD69 -> 352.483 | BA69: =S69*$Y$4 -> 50.79 | BG69: =S69+BA69 -> 350.79
B70: PARTNERS UP | C70: =COUNTA(J3:J14,J22:J40) -> 8 | D70: =IFERROR(C70/C$69,"-") -> 0.28571429 | E70: =C70 -> 8 | F70: =D70 -> 0.28571429 | I70: Bonus CREW | J70: 0.002 | K70: Suggested crew bonus | M70: =C9*J70 -> 620 | P70: 600 | S70: =V41+V66 -> 400 | AD70: =P70*$Y$4 -> 101.58 | AJ70: =P70+AD70 -> 701.58 | BA70: =S70*$Y$4 -> 67.72 | BG70: =S70+BA70 -> 467.72
B71: CREW UP (W/O MANAGERS) | C71: =COUNTA(J22:J40) -> 2 | D71: =IFERROR(C71/C$69,"-") -> 0.071428571 | E71: =C71 -> 2 | F71: =D71 -> 0.071428571 | I71: Wyksięgowanie PFRON Manager(pamiętaj żeby wpisać PFRON ze znakiem (-) przy wyksięgowaniu | P71: 0 | AJ71: =P71+AD71 -> 0
B72: CERW UZ | C72: =COUNTA(J44:J65) -> 20 | D72: =IFERROR(C72/C$69,"-") -> 0.71428571 | E72: =C72 -> 20 | F72: =D72 -> 0.71428571 | I72: Wyksięgowanie PFRON Crew (pamiętaj żeby wpisać PFRON ze znakiem (-) przy wyksięgowaniu | P72: 0 | AJ72: =P72+AD72 -> 0 | BG72: =S72+BA72 -> 0
I73: ADP | P73: 600 | S73: 600 | AJ73: =P73+AD73 -> 600 | BG73: =S73+BA73 -> 600
B74: TOTAL HOURS | C74: =C36 -> 1760 | D74: =IFERROR(C74/C$74,"-") -> 1 | E74: =E36 -> 1713.5 | F74: =IFERROR(E74/E$74,"-") -> 1 | I74: Other (Koszty HR, corrections from previous month etc.) | P74: 0 | AD74: =P74*$Y$4 -> 0 | AJ74: =P74+AD74 -> 0 | BA74: =S74*$Y$4 -> 0 | BG74: =S74+BA74 -> 0
B75: PARTNERS UP HOURS | C75: =SUM(M18,M41) -> 940 | D75: =IFERROR(C75/C$74,"-") -> 0.53409091 | E75: =SUM(S18,S41) -> 880 | F75: =IFERROR(E75/E$74,"-") -> 0.51356872 | I75: PPK | J75: PPK MGR | M75: 250 | N75: PPK CREW | P75: 0 | S75: 250 | AJ75: =P75+AD75 -> 0 | BG75: =S75+BA75 -> 250
B76: CREW UP HOURS (W/O MANAGERS) | C76: =M41 -> 220 | D76: =IFERROR(C76/C$74,"-") -> 0.125 | E76: =S41 -> 205 | F76: =IFERROR(E76/E$74,"-") -> 0.11963817 | I76: Drivers | L76: TRX | M76: 220 | N76: Cost per drop YTD | P76: 14 | S76: 206 | T76: 14 | AJ76: =P76+AD76 -> 14 | BG76: =T76+BA76 -> 14
B77: CREW UZ HOURS | C77: =M66 -> 820 | D77: =IFERROR(C77/C$74,"-") -> 0.46590909 | E77: =S66 -> 833.5 | F77: =IFERROR(E77/E$74,"-") -> 0.48643128 | H77: HUMAN RENT TOTAL: | K77: =SUM(M59:M74)/C23 -> 322.93578 | P77: =SUM(P67:P75)+(M76*P76) -> 4730 | S77: =SUM(S67:S75)+(S76*T76) -> 4584 | AD77: =SUM(AD67:AD76) -> 154.063 | AJ77: =SUM(AJ67:AJ76) -> 1818.063 | BA77: =SUM(BA67:BA76) -> 118.51 | BG77: =SUM(BG67:BG76) -> 1832.51

Sheet BONUS
B1: BONUS | C1: CAP | F1: BONUS MANAGERS
B2: SM | C2: 2250 | F2: SM | G2: =SUM(G11,G16) -> 0
B3: ASM | C3: 1000 | F3: ASM | G3: =SUM(H11,H16) -> 0
B4: SSV-PM | C4: 700 | F4: SSV-PM | G4: =SUM(I11,I16) -> 0
B5: SSV-FM | C5: 700 | F5: SSV-FM | G5: =SUM(J11,J16) -> 0
B7: =VLOOKUP(CALCULATOR!$C$5,DANE!B17:F28,3,FALSE) -> Sierpień | F7: SALES BONUS KALKULATOR
C8: AOP | D8: SALES | F8: SALES | H8: AOP | I8: index | J8: % of Cap
B9: STYCZEŃ | C9: =VLOOKUP($D$8,AOP!$A$2:$Z$100,VLOOKUP(B9,DANE!$B$17:$C$28,2,FALSE),FALSE) -> #N/A | F9: =IF(B7=B9,D9,IF(B7=B10,D10,IF(B7=B11,D11,IF(B7=B12,D12,IF(B7=B13,D13,IF(B7=B14,D14,IF(B7=B15,D15,IF(B7=B16,D16,IF(B7=B17,D17,IF(B7=B18,D18,IF(B7=B19,D19,IF(B7=B20,D20)))))))))))) -> 0 | H9: =IF(B7=B9,C9,IF(B7=B10,C10,IF(B7=B11,C11,IF(B7=B12,C12,IF(B7=B13,C13,IF(B7=B14,C14,IF(B7=B15,C15,IF(B7=B16,C16,IF(B7=B17,C17,IF(B7=B18,C18,IF(B7=B19,C19,IF(B7=B20,C20)))))))))))) -> #N/A | I9: =IFERROR(ROUND(F9/H9,2),0) -> 0 | J9: =IF(I9>F20,G20,IF(I9<F36,G36,VLOOKUP(I9,F20:G36,2,FALSE))) -> 0
B10: LUTY | C10: =VLOOKUP($D$8,AOP!$A$2:$Z$100,VLOOKUP(B10,DANE!$B$17:$C$28,2,FALSE),FALSE) -> #N/A | F10: BONUS FOR MANAGER | G10: =F2 -> SM | H10: =F3 -> ASM | I10: =F4 -> SSV-PM | J10: =F5 -> SSV-FM
B11: MARZEC | C11: =VLOOKUP($D$8,AOP!$A$2:$Z$100,VLOOKUP(B11,DANE!$B$17:$C$28,2,FALSE),FALSE) -> #N/A | G11: =IF($J$9=0,"brak premii",$C$2*$J$9) -> brak premii | H11: =IF($J$9=0,"brak premii",$C$3*$J$9) -> brak premii | I11: =IF($J$9=0,"brak premii",$C$4*$J$9) -> brak premii | J11: =IF($J$9=0,"brak premii",$C$5*$J$9) -> brak premii
B12: KWIECIEŃ | C12: =VLOOKUP($D$8,AOP!$A$2:$Z$100,VLOOKUP(B12,DANE!$B$17:$C$28,2,FALSE),FALSE) -> #N/A | F12: OPS profit BONUS KALKULATOR
B13: MAJ | C13: =VLOOKUP($D$8,AOP!$A$2:$Z$100,VLOOKUP(B13,DANE!$B$17:$C$28,2,FALSE),FALSE) -> #N/A | F13: OPS profit | H13: AOP | I13: index | J13: % of Cap
B14: CZERWIEC | C14: =VLOOKUP($D$8,AOP!$A$2:$Z$100,VLOOKUP(B14,DANE!$B$17:$C$28,2,FALSE),FALSE) -> #N/A | F14: =ROUND(IF(B7=B22,D22,IF(B7=B23,D23,IF(B7=B24,D24,IF(B7=B25,D25,IF(B7=B26,D26,IF(B7=B27,D27,IF(B7=B28,D28,IF(B7=B29,D29,IF(B7=B30,D30,IF(B7=B31,D31,IF(B7=B32,D32,IF(B7=B33,D33)))))))))))),3) -> 0 | H14: =IF(B7=B22,C22,IF(B7=B23,C23,IF(B7=B24,C24,IF(B7=B25,C25,IF(B7=B26,C26,IF(B7=B27,C27,IF(B7=B28,C28,IF(B7=B29,C29,IF(B7=B30,C30,IF(B7=B31,C31,IF(B7=B32,C32,IF(B7=B33,C33)))))))))))) -> #N/A | I14: =ROUND(IFERROR(F14/H14,0),2) -> 0 | J14: =IF(I14>H20,I20,IF(I14<H36,I36,VLOOKUP(I14,H20:I36,2,FALSE))) -> 0
B15: LIPIEC | C15: =VLOOKUP($D$8,AOP!$A$2:$Z$100,VLOOKUP(B15,DANE!$B$17:$C$28,2,FALSE),FALSE) -> #N/A | F15: BONUS FOR MANAGER | G15: =F2 -> SM | H15: =F3 -> ASM | I15: =F4 -> SSV-PM | J15: =F5 -> SSV-FM
B16: SIERPIEŃ | C16: =VLOOKUP($D$8,AOP!$A$2:$Z$100,VLOOKUP(B16,DANE!$B$17:$C$28,2,FALSE),FALSE) -> #N/A | G16: =IF($J$14=0,"brak premii",$C$2*$J$14) -> brak premii | H16: =IF($J$14=0,"brak premii",$C$3*$J$14) -> brak premii | I16: =IF($J$14=0,"brak premii",$C$4*$J$14) -> brak premii | J16: =IF($J$14=0,"brak premii",$C$5*$J$14) -> brak premii
B17: WRZESIEŃ | C17: =VLOOKUP($D$8,AOP!$A$2:$Z$100,VLOOKUP(B17,DANE!$B$17:$C$28,2,FALSE),FALSE) -> #N/A
B18: PAŹDZIERNIK | C18: =VLOOKUP($D$8,AOP!$A$2:$Z$100,VLOOKUP(B18,DANE!$B$17:$C$28,2,FALSE),FALSE) -> #N/A | F18: BONUS CALCULATIONS L2-L4
B19: LISTOPAD | C19: =VLOOKUP($D$8,AOP!$A$2:$Z$100,VLOOKUP(B19,DANE!$B$17:$C$28,2,FALSE),FALSE) -> #N/A | F19: Sales vs AOP | G19: % of Cap | H19: OPS profit vs AOP | I19: % of cap | J19: max % of cap
B20: GRUDZIEŃ | C20: =VLOOKUP($D$8,AOP!$A$2:$Z$100,VLOOKUP(B20,DANE!$B$17:$C$28,2,FALSE),FALSE) -> #N/A | F20: 1.1 | G20: 0.75 | H20: 1.1 | I20: 0.75 | J20: 1.5
C21: AOP | D21: OPS PROFIT | F21: 1.09 | G21: 0.73 | H21: 1.09 | I21: 0.72 | J21: 1.45
B22: STYCZEŃ | C22: =ROUND(VLOOKUP($D$21,AOP!$A$2:$Z$100,VLOOKUP(B22,DANE!$B$17:$E$28,4,FALSE),FALSE),3) -> #N/A | F22: 1.08 | G22: 0.7 | H22: 1.08 | I22: 0.7 | J22: 1.4
B23: LUTY | C23: =ROUND(VLOOKUP($D$21,AOP!$A$2:$Z$100,VLOOKUP(B23,DANE!$B$17:$E$28,4,FALSE),FALSE),3) -> #N/A | F23: 1.07 | G23: 0.68 | H23: 1.07 | I23: 0.67 | J23: 1.35
B24: MARZEC | C24: =ROUND(VLOOKUP($D$21,AOP!$A$2:$Z$100,VLOOKUP(B24,DANE!$B$17:$E$28,4,FALSE),FALSE),3) -> #N/A | F24: 1.06 | G24: 0.65 | H24: 1.06 | I24: 0.65 | J24: 1.3
B25: KWIECIEŃ | C25: =ROUND(VLOOKUP($D$21,AOP!$A$2:$Z$100,VLOOKUP(B25,DANE!$B$17:$E$28,4,FALSE),FALSE),3) -> #N/A | F25: 1.05 | G25: 0.63 | H25: 1.05 | I25: 0.62 | J25: 1.25
B26: MAJ | C26: =ROUND(VLOOKUP($D$21,AOP!$A$2:$Z$100,VLOOKUP(B26,DANE!$B$17:$E$28,4,FALSE),FALSE),3) -> #N/A | F26: 1.04 | G26: 0.6 | H26: 1.04 | I26: 0.6 | J26: 1.2
B27: CZERWIEC | C27: =ROUND(VLOOKUP($D$21,AOP!$A$2:$Z$100,VLOOKUP(B27,DANE!$B$17:$E$28,4,FALSE),FALSE),3) -> #N/A | F27: 1.03 | G27: 0.58 | H27: 1.03 | I27: 0.57 | J27: 1.15
B28: LIPIEC | C28: =ROUND(VLOOKUP($D$21,AOP!$A$2:$Z$100,VLOOKUP(B28,DANE!$B$17:$E$28,4,FALSE),FALSE),3) -> #N/A | F28: 1.02 | G28: 0.55 | H28: 1.02 | I28: 0.55 | J28: 1.1
B29: SIERPIEŃ | C29: =ROUND(VLOOKUP($D$21,AOP!$A$2:$Z$100,VLOOKUP(B29,DANE!$B$17:$E$28,4,FALSE),FALSE),3) -> #N/A | F29: 1.01 | G29: 0.53 | H29: 1.01 | I29: 0.52 | J29: 1.05
B30: WRZESIEŃ | C30: =ROUND(VLOOKUP($D$21,AOP!$A$2:$Z$100,VLOOKUP(B30,DANE!$B$17:$E$28,4,FALSE),FALSE),3) -> #N/A | F30: 1 | G30: 0.5 | H30: 1 | I30: 0.5 | J30: 1
B31: PAŹDZIERNIK | C31: =ROUND(VLOOKUP($D$21,AOP!$A$2:$Z$100,VLOOKUP(B31,DANE!$B$17:$E$28,4,FALSE),FALSE),3) -> #N/A | F31: 0.99 | G31: 0.33 | H31: 0.99 | I31: 0.32 | J31: 0.65
B32: LISTOPAD | C32: =ROUND(VLOOKUP($D$21,AOP!$A$2:$Z$100,VLOOKUP(B32,DANE!$B$17:$E$28,4,FALSE),FALSE),3) -> #N/A | F32: 0.98 | G32: 0.23 | H32: 0.98 | I32: 0.22 | J32: 0.45
B33: GRUDZIEŃ | C33: =ROUND(VLOOKUP($D$21,AOP!$A$2:$Z$100,VLOOKUP(B33,DANE!$B$17:$E$28,4,FALSE),FALSE),3) -> #N/A | F33: 0.97 | G33: 0.18 | H33: 0.97 | I33: 0.17 | J33: 0.35
F34: 0.96 | G34: 0.13 | H34: 0.96 | I34: 0.12 | J34: 0.25
F35: 0.95 | G35: 0.1 | H35: 0.95 | I35: 0.1 | J35: 0.2
F36: 0.94 | G36: 0 | H36: 0.94 | I36: 0 | J36: 0

Sheet AOP

Sheet TPLH PLAN
B1: Styczeń | C1: Luty | D1: Marzec | E1: Kwiecień | F1: Maj | G1: Czerwiec | H1: Lipiec | I1: Sierpień | J1: Wrzesień | K1: Październik | L1: Listopad | M1: Grudzień
A2: TPLH PLAN AOP

Sheet Fields Description
A1: Poniżej znajdują się wskaźniki i sposób ich obliczania w COL Report, z którego zaciągane są dane do DOS+. Aby być spójnymi między raportami, wszystkie wskaźniki w COL Kalkulatorze są wyliczane tak samo jak w COL Report.
B2: Column number in the report | C2: name of column | D2: Unit | E2: what does it mean ? | F2: Formula
B3: Groups
B4: 1 | C4: District | E4: Nazwa dystryktu, do którego należy restauracja
B5: 2 | C5: Region | E5: Nazwa regionu, do którego należy restauracja
B6: 3 | C6: Cost center | E6: Numer MPK restauracji z SAP
B7: 4 | C7: Restaurant | E7: Nazwa restauracji
B8: 5 | C8: Pacesetter Group | E8: Nazwa grupy pacesetterowej, do której należy restauracja
B9: 6 | C9: Month | E9: Nazwa miesiąca
B10: Better/Worse vs LY
B11: 7 | C11: Total COL % B / W vs LY | D11: [%] | E11: Łączne koszty COL (jako % od sprzedaży,dane z P&L) w porównaniu do łącznych kosztów COL (jako % od sprzedaży,dane z P&L) z tego samego miesiaca zeszłego roku. | F11: Total COL% - Total COL% LY
B12: 8 | C12: Total MPT B / W vs LY | D12: [min] | E12: Total MPT z danego miesiaca w porównaniu do Total MPT z tego samego miesiąca zeszłego roku | F12: Total MPT - Total MPT LY
B13: 9 | C13: Sales per total working hour B / W vs LY | D13: [PLN/hour] | E13: Sales per working hour crew i Managerów z danego miesiaca w porównaniu do Sales per working hour crew i Managerów z tego samego miesiąca zeszłego roku | F13: Sales per total working hour - Sales per total working hour LY
B14: 10 | C14: TPLH B / W vs LY (tylko SBX) | D14: [min] | E14: TPLH z danego miesiaca w porównaniu do TPLH z tego samego miesiąca zeszłego roku | F14: TPLH - TPLY LY
B15: 11 | C15: Crew MPT B / W vs LY | D15: [%] | E15: Crew MPT z danego miesiaca w porównaniu do Crew MPT z tego samego miesiąca zeszłego roku | F15: Crew MPT - Crew MPT LY
B16: 12 | C16: Transactions Index | D16: [%] | E16: Transakcje dla aktualnego miesiąca dzielone przez transakcje dla tego samego miesiąca zeszłego roku | F16: (Liczba transkacji/Liczbę transakcji LY)*100
B17: 13 | C17: Sales Index | D17: [%] | E17: Sprzedaż dla aktualnego miesiąca dzielona przez sprzedaż dla tego samego miesiąca zeszłego roku | F17: (Wartość sprzedazy/Wartosc sprzedazy LY)*100
B18: 14 | C18: Crew working hours B / W vs LY | D18: [%] | E18: Łączne godziny przepracowane crew z danego miesiaca w porówaniu do łącznych godzin przepracowanych crew z tego samego miesiąca zeszłego roku | F18: (Total crew working hours/Total crew working hours LY)*100
B19: 15 | C19: Crew non working hours B / W vs LY | D19: [%] | E19: Łączne godziny nieprzepracowane crew z danego miesiaca w porówaniu do łącznych godzin nieprzepracowanych crew z tego samego miesiąca zeszłego roku | F19: (Total crew non working hours/Total crew non working hours LY)*100
B20: 16 | C20: BASE WAGE B / W vs LY | D20: [%] | E20: Średnia stawka crew na godzinę przepracowaną w danym miesiacu do średniej stawki crew na godzinę przepracowaną z tego samego miesiąca zeszłego roku | F20: (Base Wage/Base Wage LY)* 100
B21: 17 | C21: COL Crew B\W vs LY | D21: [%] | E21: Całkowite koszty crew (jako % od sprzedaży) w danym miesiącu w porówaniu do całkowitych kosztów crew (jako % od sprzadży) z tego samego miesiąca zeszłego roku | F21: (Col Crew/Col Crew LY)*100
B22: 18 | C22: COL Mgmt B\W vs. LY | D22: [%] | E22: Całkowite koszty managerów (jako % od sprzedaży) w danym miesiącu w porówaniu do całkowitych kosztów managerów (jako % od sprzadży) z tego samwego miesiąca zeszłego roku | F22: (Col Managers/Col Managers LY)*100
B23: COL % - dane z P&L
B24: 19 | C24: Mgmt % | D24: [%] | E24: Całkowite koszty managerów jako % od sprzedaży (dane z P&L; łączne koszty zawierające wynagrodzenie podstawowe, ZUS, bonusy, wakacje, zwolnienia lekarskie, kafeterię, ekwiwalenty, nagrody, rezerwy, itp.) | F24: Col Managers/sales
B25: 20 | C25: Crew % (HOH, BOH and delivery employed by AmRest) | D25: [%] | E25: Całkowite koszty crew (HOH, BOH, umowy zlecenie oraz delivery, ale tylko osoby zatrudniane przez AmRest) jako % od sprzedaży (dane z P&L; łączne koszty zawierające wynagrodzenie podstawowe, ZUS, bonusy, ekwiwalent, wakacje, zwolnienia lekarskie, nagrody, rezerwy, itp.) | F25: Col crew/sales
B26: 21 | C26: Delivery % (outside services) | D26: [%] | E26: Koszty kierowców delivery (tylko osoby na działalności, świadczące usługi na rzecz AmRest) jako % od sprzedaży (dane z P&L; tylko usługi obce ) | F26: Col delivery/sales
B27: 22 | C27: TOTAL COL % | D27: [%] | E27: Łączne koszty COL jako % od sprzedaży (dane z P&L) | F27: Total Col/sales | G27: COL%
B28: Managers - dane z HR Department
B29: 23 | C29: Total MPT | D29: [min/trans] | E29: Wskaźnik efektywności managerów i crew liczony jako łączna ilość minut pracy managerów i crew przypadająca na jedną transakcję. | F29: Total MPT = ( łączne godziny pracy managerów + łączne godziny pracy crew - łączne godziny pracy delivery) * 60 / Trans
B30: 24 | C30: Sales per total working hours | D30: [PLN/hour] | E30: Średnia wartość sprzedaży przypadająca na jedną przepracowaną godzinę crew oraz managerów | F30: Sales per working hour = Sales / (Total crew working hours + Total managers working hours) | G30: SPLH
B31: 25 | C31: TPLH (tylko dla brandu SBX) | D31: [trans/min] | E31: Transakcje podzielone przez ilość przepracowanych godzin załogi i managerów łącznie | F31: TPLH = Liczba transakcji / Liczba godzin przepracowanych | G31: TPLH (Total)
B32: 26 | C32: Total number of managers | D32: [osoby] | E32: Całkowita liczba managerów zatrudnionych w restauracji wliczając managerów pracujących w danym miesiącu na stanowiskach oraz managerów na urlopach macierzyńskich, wychowawczych, w ciąży oraz na bezpłatnych urlopach powyżej 30 dni.
B33: 27 | C33: Ideal structure | D33: [osoby] | E33: Liczba mangerów zgodnie z idelaną strukturą
B34: 28 | C34: Number of managers - charged in P&L | D34: [osoby] | E34: Liczba managerów zgodnie z podziałem kosztowym (może być róznica między kolumną 28 i 29 gdy manager pracuje w restauracji X, natomiast jego koszty są księgowane w restauracji Y)
B35: 29 | C35: Number of working managers | D35: [osoby] | E35: Liczba managerów pracujących w danym miesiącu w restauracji, z wykluczeniem osób na urlopach macierzyńskich, wychowawczych, w ciąży lub na bezpłatnym urlopie powyżej 30 dnia.
B36: 30 | C36: Total managers working hours | D36: [hours] | E36: Łączne godziny przepracowane managerów, którzy posiadają miesięczną pensję managerską. Wliczane są tylko godziny managerów, którzy faktycznie pracowali w danym miesiącu w restauracji. Osoby na urlopach macierzyńskich, wychowawczych, w ciąży lub na bezpłatnym urlopie powyżej 30 dni są wykluczone z raportu. | G36: Planowany czas pracy
B37: 31 | C37: Total managers non working hours | D37: [hours] | E37: Łączne godziny nieprzepracowane managerów: 1. godzin urlopu wypoczynkowego, 2. godziny zwolnień lekarskich, ale tylko godziny płatne przez AmRest | F37: Total managers non working hours = vacation hours + hours for sick leave paid by the Company | G37: Urlop + zwolnienia lekarskie
B38: 32 | C38: Managers vacation hours (urlop wypoczynkowy) | D38: [hours] | E38: Godziny nieprzepracowane - urlop wypoczynkowy Managerów | G38: Urlop
B39: 33 | C39: Managers sick leave hours paid by the Company | D39: [hours] | E39: Godziny nieprzepracowane Managerów - zwolnienia lekarskie, ale tylko godziny płatne przez AmRest | G39: Zwolnienie lekarskie
B40: 34 | C40: % managers non working hours of all managers hours | D40: [%] | E40: Udział godzin nieprzepracowanych managerów do łącznej liczby godzin managerów (przepracowanych i nieprzepracowanych) | F40: % managers non working hours = Łączne godziny nieprzepracowane managerów / (Łączne godziny przepracowane managerów + Łączne godziny nieprzepracowane managerów)
B41: Crew - dane z HR Department
B42: 35 | C42: Crew MPT | D42: [min/trans] | E42: Wskaźnik efektywności crew liczony jako średnia ilość minut pracy crew przypadająca na jedną transakcję | F42: Crew MPT = (Łączne godziny pracy crew - Łączne godziny pracy delivery) * 60 / Trans
B43: 36 | C43: Sales per crew working hour | D43: [PLN/hour] | E43: Średnia wartość sprzedaży przypadająca na jedną godzinę pracy crew | F43: Sales per crew working hour = Sales / Total crew working hours | G43: SPLH
B44: 37 | C44: Rotacja | D44: [%] | E44: Rotacja załogi miesięczna | F44: Rotacja = Liczba zwolnionych w danym mieisacu/Stan załogi na koniec miesiąca
B45: 38 | C45: Sales | D45: [PLN] | E45: Wartość sprzedaży z P&La | G45: SALES
B46: 39 | C46: Trans | D46: [trans] | E46: Liczba transakcji zrealizowanych w restauracji we wszystkich kanałach sprzedaży (dane z P&L) | G46: TRANSACTIONS
B47: 40 | C47: Total number of crew | D47: [osoby] | E47: Łączna ilość osób zatrudnionych na stanowisku crew (umowy o pracę i zlecenie) | F47: Total number of crew = crew in regular contract + crew in civil contracts in training + crew in civil contract after training
B48: 41 | C48: Number of crew (regular contracts) | D48: [osoby] | E48: Osoby zatrudnione na umowę o pracę
B49: 42 | C49: Number of crew (civil contracts in training) | D49: [osoby] | E49: Osoby zatrudnione na umowę zlecenie na czas szkolenia
B50: 43 | C50: Number of crew (civil contracts after training) | D50: [osoby] | E50: Osoby zatrudnione na umowę zlecenie poszkoleniową
B51: 44 | C51: Total crew working hours | D51: [hours] | E51: Łączne godziny przepracowane crew składające się z: 1. godzin przepracowanych HOH & FOH, 2. godzin przepracowanych osób zatrudnionych na umowy zlecenie, 3. godziny przepracowane delivery (ale tylko osoby zatrudniane przez AmRest) 4. godziny przepracowane w nocy 5. godziny nadliczbowe | F51: Total crew working hours = godziny przepracowane HOH i FOH + godziny przepracowane w ramach umów zlecenie + godziny przepracowane delivery (tylko osoby zatrudniane przez AmRest) + godziny przepracowane w nocy + godziny nadliczbowe | G51: CREW WORKING HOURS
B52: 45 | C52: Total HOH and FOH working hours | D52: [hours] | E52: Godziny przepracowane HOH i FOH (wliczamy wszystkie godziny zgodnie z kartą pracy, także godziny treningu, sprzątania oraz godziny przed otwarciem i po zamknięciu restauracji, z wykluczeniem godziny nocnych i nadliczbowych)
B53: 46 | C53: Total weekends hours (tylko dla Czech) | D53: [hours] | E53: Godziny przepracowane podczas weekendu
B54: 47 | C54: Total civil contracts working hours (or DPP and DPC contracts working hours in Czech or Students Contracts in Russia) | D54: [hours] | E54: Godziny przepracowane osób zatrudnionych na umowy zlecenie CZ, RU
B55: 48 | C55: Civil contract in training working hours (tylko dla PL) | D55: [hours] | E55: Godziny przepracowane osób zatrudnionych na umowy zlecenie szkoleniowe
B56: 49 | C56: Civil contracts after training working hours (tylko dla PL) | D56: [hours] | E56: Godziny przepracowane osób zatrudnionych na umowy zlecenie poszkoleniowe
B57: 50 | C57: Total delivery working hours | D57: [hours] | E57: Godziny przepracowane delivery (ale tylko osoby identyfikowane w karcie pracy, zatrudniane przez AmRest)
B58: 51 | C58: Total night working hours | D58: [hours] | E58: Godziny przepracowane w nocy ( po 23:00)
B59: 52 | C59: Total crew non working hours | D59: [hours] | E59: Łączne godziny nieprzepracowane crew składające się z: 1. godzin urlopu wypoczynkowego, 2. godzin urlopu okolicznościowego, 3. godzin nieobecności (usprawiedliwionej i nieusprawiedliwionej) 4. godziny zwolnień lekarskich, ale tylko godziny płatne przez AmRest | F59: Total crew non working hours = godziny urlopu wypoczynkowego + godziny urlopu okolicznościowego + godziny nieobecności usprawiedliwionych i nieusprawiedliwionych + godziny zwolnień lekarskich płatnych przez AmRest | G59: H
G60: SICK LEAVE
B61: 53 | C61: Vacation hours (urlop wypoczynkowy) | D61: [hours] | E61: Godziny nieprzepracowane - urlop wypoczynkowy crew | G61: Urlop
B62: 54 | C62: Holiday hours (urlop okolicznościowy) | D62: [hours] | E62: Godziny nieprzepracowane - urlop okolicznościowy crew (np. z okazji ślubu, śmierci członka rodziny)
B63: 55 | C63: Excused absence hours | D63: [hours] | E63: Godziny nieprzepracowane - nieobecności usprawiedliwione crew (np. wyjście do sądu, oddanie krwi)
B64: 56 | C64: Unexcused absence hours | D64: [hours] | E64: Godziny nieprzepracowane - nieobecności nieusprawiedliwione crew
B65: 57 | C65: Sick leave hours paid by the Company | D65: [hours] | E65: Godziny nieprzepracowane - zwolnienia lekarskie, ale tylko godziny płatne przez AmRest | G65: Zwolnienie lekarskie
B66: 58 | C66: % crew non working hours of all crew hours | D66: [%] | E66: Udział godzin nieprzepracowanych crew do łącznej liczby godzin crew (przepracowanych i nieprzepracowanych) | F66: % crew non working hours = Łączne godziny nieprzepracowane crew / (Łączne godziny przepracowane crew + Łączne godziny nieprzepracowane crew)
B67: 59 | C67: Overtime hours | D67: [hours] | E67: Godziny nadliczbowe crew (godziny ponad miesięczny wymiar czasu pracy)
B68: 60 | C68: Payment for overtime hours | D68: [PLN] | E68: Wynagrodzenie za godziny nadliczbowe (podstawowa stawka godzinowa plus premia za nadgodziny: 50% za nadgodziny w dzień i 100% za nadgodziny w nocy)
B69: 61 | C69: Undertime hours (tylko dla PL) | D69: [hours] | E69: Niedogodziny (godziny, za które płacimy w sytuacji gdy pracownik przepracował mniej godzin niż ma w umowie o pracę)
B70: 62 | C70: Payment for undertime hours (tylko dla PL) | D70: [PLN] | E70: Wynagrodzenie za niedogodziny (płacimy w sytuacji, gdy pracownik przepracował mniej godzin niż ma określone w umowie o pracę)
B71: Crew wage - dane z HR Department
B72: 63 | C72: Base wage (Avg crew wage per working hour) | D72: [local currency] | E72: Średnia stawka crew na godzinę przepracowaną. Do wyliczenia stawki wykorzystuje się podstawowe wynagrodzenie brutto ( z ZUS) za godziny przepracowane. Stawka ta nie zawiera: 1. dodatku za pracę w godzinach nocnych, dodatku za godziny nadliczbowe, 2. dopłaty do najniższego wynagrodzenie (gwarantowanego przez prawo) 3. płatności za godziny nieprzepracowane takie jak urlopy, zwolnienia lekarskie 4. ekwiwalentu BHP ('BUTY') 5. bonusów | F72: Base wage = Podstawowe wynagrodzenie brutto za godziny przepracowane / Łączne godziny przepracowane crew
B73: 64 | C73: Full wage (Avg crew wage per all hours) | D73: [local currency] | E73: Średnia stawka crew na godzinę (łącznie przepracowaną i nieprzepracowaną). Do wyliczenia stawki wykorzystuje się wynagrodzenie brutto zawierające takie składowe jak: 1. ZUS 2. dodatek za pracę w godzinach nocnych, dodatek za godziny nadliczbowe, 3. dopłata do najniższego wynagrodzenie (gwarantowanego przez prawo) 4. wynagrodzenie za godziny nieprzepracowane takie jak: urlopy, zwolnienia lekarskie Stawka ta nie zawiera ekwiwalentu BHP ('BUTY') oraz bonusów. | F73: Full wage = Wynagrodzenie brutto za godziny przepracowane i nieprzepracowane łącznie / (Łączne godziny przepracowane crew + Łączne godziny nieprzepracowane crew)
B74: 65 | C74: % change vs. last year BASE WAGE | D74: [%] | E74: Zmiana Base wage w porównaniu ze stawką jaka była w tym samym miesiącu w roku ubiegłym
B75: 66 | C75: Extra payment for the lowest wages (tylko dla Polski) | D75: [local currency] | E75: Dopłata do najniższego wynagrodzenia, gwarantowanego przez państwo (dotyczy tylko osób ze stawką niższą niż stawka minimalna w danym miesiącu, która zależy od ilości dni pracujących w miesiącu)

Sheet DANE
A1: MANAGER | J1: CZAS PRACY | O1: stawka minimalna od stycznia
A2: PL | B2: Pozycja | C2: Wymiar etatu | D2: Pozycje Barista | E2: Social insurance | F2: Equivalent | G2: PFRON | H2: Comp&Ben | I2: JPA Accrual | J2: 2025 | K2: Liczba Dni Pracy | L2: Czas Pracy | M2: Min stawka godzinowa | N2: Dodatek za godz. nocne | O2: 4666 | P2: Calk | Q2: =CALCULATOR!C32 -> Plan A | R2: =VLOOKUP($Q$2,$Q$4:$S$6,2,0) -> 0.11617064 | S2: =VLOOKUP($Q$2,$Q$4:$S$6,3,0) -> 4.8144359 | V2: Staffing | AA2: MPK | AB2: Nazwa Kawiarni
B3: SM | C3: 1 | E3: 0.1693 | F3: 300 | G3: 200 | H3: 300 | I3: 367 | J3: STYCZEŃ | K3: 21 | L3: 168 | M3: =$O$2/L3 -> 27.77381 | N3: =M3*0.2 -> 5.5547619 | O3: stawka minimalna od lipca | V3: STYCZEŃ | W3: =OFFSET(#REF!,7,MATCH(V3,#REF!,0)+3) -> #REF! | X3: =VLOOKUP($W3,$Q$4:$S$6,2,FALSE) -> #REF! | Y3: =VLOOKUP($W3,$Q$4:$S$6,3,FALSE) -> #REF! | AA3: 108001 | AB3: SBX Warszawa Al. Jerozolimskie
B4: ASM | C4: 0.75 | F4: 300 | H4: 250 | J4: LUTY | K4: 20 | L4: 160 | M4: =$O$2/L4 -> 29.1625 | N4: =M4*0.2 -> 5.8325 | Q4: Plan A | R4: 0.11617064 | S4: 4.8144359 | V4: LUTY | W4: =OFFSET(#REF!,7,MATCH(V4,#REF!,0)+3) -> #REF! | X4: =VLOOKUP(W4,$Q$4:$S$6,2,FALSE) -> #REF! | Y4: =VLOOKUP($W4,$Q$4:$S$6,3,FALSE) -> #REF! | AA4: 108002 | AB4: SBX Warszawa Zodiak
B5: SSV-PM | C5: 0.5 | F5: 350 | H5: 200 | J5: MARZEC | K5: 21 | L5: 168 | M5: =$O$2/L5 -> 27.77381 | N5: =M5*0.2 -> 5.5547619 | O5: 4666 | Q5: Plan B | R5: 0.11890051 | S5: 5.8833006 | V5: MARZEC | W5: =OFFSET(#REF!,7,MATCH(V5,#REF!,0)+3) -> #REF! | X5: =VLOOKUP(W5,$Q$4:$S$6,2,FALSE) -> #REF! | Y5: =VLOOKUP($W5,$Q$4:$S$6,3,FALSE) -> #REF! | AA5: 108003 | AB5: SBX Wroclaw Grunwaldzki Center
B6: SSV-FM | C6: 0.25 | F6: 350 | H6: 200 | J6: KWIECIEŃ | K6: 21 | L6: 168 | M6: =$O$2/L6 -> 27.77381 | N6: =M6*0.2 -> 5.5547619 | Q6: Plan C | R6: 0.073029331 | S6: 8.0872137 | V6: KWIECIEŃ | W6: =OFFSET(#REF!,7,MATCH(V6,#REF!,0)+3) -> #REF! | X6: =VLOOKUP(W6,$Q$4:$S$6,2,FALSE) -> #REF! | Y6: =VLOOKUP($W6,$Q$4:$S$6,3,FALSE) -> #REF! | AA6: 108004 | AB6: SBX Warszawa Nowy Swiat
B7: SSV | F7: 350 | H7: 200 | J7: MAJ | K7: 20 | L7: 160 | M7: =$O$2/L7 -> 29.1625 | N7: =M7*0.2 -> 5.8325 | V7: MAJ | W7: =OFFSET(#REF!,7,MATCH(V7,#REF!,0)+3) -> #REF! | X7: =VLOOKUP(W7,$Q$4:$S$6,2,FALSE) -> #REF! | Y7: =VLOOKUP($W7,$Q$4:$S$6,3,FALSE) -> #REF! | AA7: 108013 | AB7: SBX Wroclaw Sky Tower
B8: BARISTA | J8: CZERWIEC | K8: 20 | L8: 160 | M8: =$O$2/L8 -> 29.1625 | N8: =M8*0.2 -> 5.8325 | V8: CZERWIEC | W8: =OFFSET(#REF!,7,MATCH(V8,#REF!,0)+3) -> #REF! | X8: =VLOOKUP(W8,$Q$4:$S$6,2,FALSE) -> #REF! | Y8: =VLOOKUP($W8,$Q$4:$S$6,3,FALSE) -> #REF! | AA8: 108017 | AB8: SBX Warszawa Gruba Kaska
B9: BT | E9: 0.1693 | F9: 0.85 | G9: 200 | J9: LIPIEC | K9: 23 | L9: 184 | M9: =$O$5/L9 -> 25.358696 | N9: =M9*0.2 -> 5.0717391 | P9: ON | V9: LIPIEC | W9: =OFFSET(#REF!,7,MATCH(V9,#REF!,0)+3) -> #REF! | X9: =VLOOKUP(W9,$Q$4:$S$6,2,FALSE) -> #REF! | Y9: =VLOOKUP($W9,$Q$4:$S$6,3,FALSE) -> #REF! | AA9: 108023 | AB9: SBX Warszawa Galaxy IL
B10: B | J10: SIERPIEŃ | K10: 20 | L10: 160 | M10: =$O$5/L10 -> 29.1625 | N10: =M10*0.2 -> 5.8325 | P10: Tak | V10: SIERPIEŃ | W10: =OFFSET(#REF!,7,MATCH(V10,#REF!,0)+3) -> #REF! | X10: =VLOOKUP(W10,$Q$4:$S$6,2,FALSE) -> #REF! | Y10: =VLOOKUP($W10,$Q$4:$S$6,3,FALSE) -> #REF! | AA10: 108025 | AB10: SBX Krakow Galeria Krakowska
B11: LOBBY | J11: WRZESIEŃ | K11: 22 | L11: 176 | M11: =$O$5/L11 -> 26.511364 | N11: =M11*0.2 -> 5.3022727 | V11: WRZESIEŃ | W11: =OFFSET(#REF!,7,MATCH(V11,#REF!,0)+3) -> #REF! | X11: =VLOOKUP(W11,$Q$4:$S$6,2,FALSE) -> #REF! | Y11: =VLOOKUP($W11,$Q$4:$S$6,3,FALSE) -> #REF! | AA11: 108026 | AB11: SBX Warszawa Zebra Tower
J12: PAŹDZIERNIK | K12: 23 | L12: 184 | M12: =$O$5/L12 -> 25.358696 | N12: =M12*0.2 -> 5.0717391 | V12: PAŹDZIERNIK | W12: =OFFSET(#REF!,7,MATCH(V12,#REF!,0)+3) -> #REF! | X12: =VLOOKUP(W12,$Q$4:$S$6,2,FALSE) -> #REF! | Y12: =VLOOKUP($W12,$Q$4:$S$6,3,FALSE) -> #REF! | AA12: 108029 | AB12: SBX Poznan Stary Browar
J13: LISTOPAD | K13: 18 | L13: 144 | M13: =$O$5/L13 -> 32.402778 | N13: =M13*0.2 -> 6.4805556 | V13: LISTOPAD | W13: =OFFSET(#REF!,7,MATCH(V13,#REF!,0)+3) -> #REF! | X13: =VLOOKUP(W13,$Q$4:$S$6,2,FALSE) -> #REF! | Y13: =VLOOKUP($W13,$Q$4:$S$6,3,FALSE) -> #REF! | AA13: 108036 | AB13: SBX Gdansk Galeria Baltycka ECE
J14: GRUDZIEŃ | K14: 20 | L14: 160 | M14: =$O$5/L14 -> 29.1625 | N14: =M14*0.2 -> 5.8325 | V14: GRUDZIEŃ | W14: =OFFSET(#REF!,7,MATCH(V14,#REF!,0)+3) -> #REF! | X14: =VLOOKUP(W14,$Q$4:$S$6,2,FALSE) -> #REF! | Y14: =VLOOKUP($W14,$Q$4:$S$6,3,FALSE) -> #REF! | AA14: 108039 | AB14: SBX Gdansk Manhattan Sephora
L15: średnia | M15: =SUM(M3:M14)/12 -> 28.230455 | N15: =M15*0.2 -> 5.646091 | AA15: 108040 | AB15: SBX Warszawa WFC
B16: Wyszukiwanie w AOP | D16: Wysz.w Bonus | AA16: 108045 | AB16: SBX Gdynia Swietojanska Bell
B17: Styczeń | C17: 3 | D17: Grudzień | E17: 4 | L17: Ubezpieczony | M17: Płatnik AmRest | N17: Płatnik AmRest Coffee | AA17: 108047 | AB17: SBX Katowice PKP
B18: Luty | C18: =C17+2 -> 5 | D18: Styczeń | E18: 6 | J18: Ubezpieczenia społeczne | K18: Emerytalne | L18: 0.0976 | M18: 0.0976 | N18: 0.0976 | AA18: 108050 | AB18: SBX Katowice Galeria Katowicka
B19: Marzec | C19: =C18+2 -> 7 | D19: Luty | E19: 8 | K19: Rentowe | L19: 0.015 | M19: 0.065 | N19: 0.065 | AA19: 108051 | AB19: SBX Kraków Galeria Krakowska Kiosk
B20: Kwiecień | C20: =C19+2 -> 9 | D20: Marzec | E20: 10 | K20: Chrobowe | L20: 0.0245 | AA20: 108053 | AB20: SBX Wroclaw Bielany Wroclawskie
B21: Maj | C21: =C20+2 -> 11 | D21: Kwiecień | E21: 12 | AA21: 108054 | AB21: SBX Szczecin Kaskada
B22: Czerwiec | C22: =C21+2 -> 13 | D22: Maj | E22: 14 | J22: Ubezpieczenie wypadkowe | K22: Wypadkowe | M22: 0.0067 | N22: 0.0067 | AA22: 108055 | AB22: SBX Warszawa PKP
B23: Lipiec | C23: =C22+2 -> 15 | D23: Czerwiec | E23: 16 | AA23: 108056 | AB23: SBX Wroclaw Magnolia W biegu Cafe
B24: Sierpień | C24: =C23+2 -> 17 | D24: Lipiec | E24: 18 | J24: Ubezpieczenie zdrowotne | K24: Zdrowotne | L24: 0.09 | AA24: 108058 | AB24: SBX Poznan Dworzec PKP Hall
B25: Wrzesień | C25: =C24+2 -> 19 | D25: Sierpień | E25: 20 | AA25: 108060 | AB25: SBX Poznan Pasaz M&M
B26: Październik | C26: =C25+2 -> 21 | D26: Wrzesień | E26: 22 | J26: Fundusz Pracy | M26: 0.0245 | N26: 0.0245 | AA26: 108061 | AB26: SBX Szczecin Brama Portowa Grzybek
B27: Listopad | C27: =C26+2 -> 23 | D27: Październik | E27: 24 | AA27: 108063 | AB27: SBX Katowice Silesia City Center
B28: Grudzień | C28: =C27+2 -> 25 | D28: Listopad | E28: 26 | J28: Fundusz Gwarantowanych Świadczeń Pracowniczych | M28: 0.001 | N28: 0.001 | AA28: 108064 | AB28: SBX Gdynia Galeria Riviera
M29: =SUM(M18:M28) -> 0.1948 | N29: =SUM(N18:N28) -> 0.1948 | AA29: 108065 | AB29: SBX Wroclaw Olawska
AA30: 108067 | AB30: SBX Warszawa Galeria Wilenska
AA31: 108068 | AB31: SBX Warszawa Galeria Mokotow
AA32: 108069 | AB32: SBX Gdansk OBC
AA33: 108070 | AB33: SBX Poznan Plaza
AA34: 108074 | AB34: SBX Wroclaw PKP
AA35: 108075 | AB35: SBX Wroclaw Coffee Square
AA36: 108080 | AB36: SBX Krakow Bonarka
AA37: 108081 | AB37: SBX Szczecin Galaxy KK
AA38: 108083 | AB38: SBX Krakow Rynek 27
AA39: 108084 | AB39: SBX Poznan Posnania
AA40: 108085 | AB40: SBX Sopot Sheraton Plaza Village
AA41: 108088 | AB41: SBX Poznan Posnania I floor
... AA73: 108137 | AB73: SBX Poznan Polwiejska 2
AA74: 108141
AA75: 108144 | AB75: SBX Rzeszow Galeria Rzeszow
AA76: 108145 | AB76: SBX Wroclaw Fashion Outlet
AA77: 108146 | AB77: SBX Bydgoszcz Focus
AA78: 108148 | AB78: SBX Warszawa Rondo Daszynskiego
AA79: 108149 | AB79: SBX Torun Plaza
AA80: 108150 | AB80: SBX Lubin Cuprum Arena
AA81: 108151 | AB81: SBX Gliwice Forum
AA82: 108152 | AB82: SBX Torun Stary Rynek
AA83: 108153 | AB83: SBX Warszawa Elektrownia Powisle
AA84: 108155 | AB84: SBX Lodz Sukcesja
AA85: 108156 | AB85: SBX Lublin Krakowskie Przedmiescie
AA86: 108157 | AB86: SBX Poznan Avenida
... AA96: 108171 | AB96: SBX Kielce Galeria Korona
